Workbook
Name Slicer_price_range: #N/A
Name Slicer_price_range1: #N/A
Name Slicer_Range: #N/A
Name Slicer_task5_range: #N/A

Sheet raw data
A1: Coin Name | B1: Symbol | C1: Price (USD) | D1: 1h Change (%) | E1: 1h change | F1: 24 hr change | G1: 7d change | H1: Market Cap | I1: Volume (24h) USD | J1: volume num | K1: Circulating Supply | L1: Allowed coin | M1: current price | N1: previous price | O1: price range | P1: price change | Q1: average downfall | R1: task5 range | S1: Range
A2: Bitcoin | B2: BTC | C2: $104,058.04 | D2: 0.0024 | E2: =D2 -> 0.0024 | F2: =-D2 -> -0.0024 | G2: =D2 -> 0.0024 | H2: $2.07T | I2: $43,170,391,288 | J2: =IFERROR(VALUE(SUBSTITUTE(SUBSTITUTE(Table1[[#This Row],[Volume (24h) USD]],"$",""),",","")),0) -> 43170391288 | K2: 19.88M | L2: =IF(OR(LEFT(Table1[[#This Row],[Coin Name]],1)="A",LEFT(Table1[[#This Row],[Coin Name]],1)="E",LEFT(Table1[[#This Row],[Coin Name]],1)="I",LEFT(Table1[[#This Row],[Coin Name]],1)="O",LEFT(Table1[[#This Row],[Coin Name]],1)="U",LEFT(Table1[[#This Row],[Coin Name]],1)="B",LEFT(Table1[[#This Row],[Coin Name]],1)="C",LEFT(Table1[[#This Row],[Coin Name]],1)="D"),"Yes","No") -> Yes | M2: =VALUE(SUBSTITUTE(C2,"$","")) -> 104058.04 | N2: =M2/(1+D2) -> 103808.9 | O2: =IF(M2<10,"Up to $10",">= $10") -> >= $10 | P2: =M2-N2 -> 249.14136 | Q2: =F2 -> -0.0024 | R2: =IF(M2<=5,"$0-$5",">$5") -> >$5 | S2: =IF(M2<=0.05,"$0-$0.05",IF(M2<=0.5,"$0.05-$0.5",IF(M2<=5,"$0.5-$5",IF(M2<=50,"$5-$50",">$50")))) -> >$50
A3: Ethereum | B3: ETH | C3: $2,483.59 | D3: 0.0076 | E3: =D3 -> 0.0076 | F3: =-D3 -> -0.0076 | G3: =D3 -> 0.0076 | H3: $299.51B | I3: $14,942,260,356 | J3: =IFERROR(VALUE(SUBSTITUTE(SUBSTITUTE(Table1[[#This Row],[Volume (24h) USD]],"$",""),",","")),0) -> 14942260356 | K3: 120.72M | L3: =IF(OR(LEFT(Table1[[#This Row],[Coin Name]],1)="A",LEFT(Table1[[#This Row],[Coin Name]],1)="E",LEFT(Table1[[#This Row],[Coin Name]],1)="I",LEFT(Table1[[#This Row],[Coin Name]],1)="O",LEFT(Table1[[#This Row],[Coin Name]],1)="U",LEFT(Table1[[#This Row],[Coin Name]],1)="B",LEFT(Table1[[#This Row],[Coin Name]],1)="C",LEFT(Table1[[#This Row],[Coin Name]],1)="D"),"Yes","No") -> Yes | M3: =VALUE(SUBSTITUTE(C3,"$","")) -> 2483.59 | N3: =M3/(1+D3) -> 2464.8571 | O3: =IF(M3<10,"Up to $10",">= $10") -> >= $10 | P3: =M3-N3 -> 18.732914 | Q3: =F3 -> -0.0076 | R3: =IF(M3<=5,"$0-$5",">$5") -> >$5 | S3: =IF(M3<=0.05,"$0-$0.05",IF(M3<=0.5,"$0.05-$0.5",IF(M3<=5,"$0.5-$5",IF(M3<=50,"$5-$50",">$50")))) -> >$50
A4: Tether | B4: USDT | C4: $0.9999 | D4: 0.0004 | E4: =D4 -> 0.0004 | F4: =-D4 -> -0.0004 | G4: =D4 -> 0.0004 | H4: $155.95B | I4: $60,772,601,456 | J4: =IFERROR(VALUE(SUBSTITUTE(SUBSTITUTE(Table1[[#This Row],[Volume (24h) USD]],"$",""),",","")),0) -> 60772601456 | K4: 155.94B | L4: =IF(OR(LEFT(Table1[[#This Row],[Coin Name]],1)="A",LEFT(Table1[[#This Row],[Coin Name]],1)="E",LEFT(Table1[[#This Row],[Coin Name]],1)="I",LEFT(Table1[[#This Row],[Coin Name]],1)="O",LEFT(Table1[[#This Row],[Coin Name]],1)="U",LEFT(Table1[[#This Row],[Coin Name]],1)="B",LEFT(Table1[[#This Row],[Coin Name]],1)="C",LEFT(Table1[[#This Row],[Coin Name]],1)="D"),"Yes","No") -> No | M4: =VALUE(SUBSTITUTE(C4,"$","")) -> 0.9999 | N4: =M4/(1+D4) -> 0.9995002 | O4: =IF(M4<10,"Up to $10",">= $10") -> Up to $10 | P4: =M4-N4 -> 0.00039980008 | Q4: =F4 -> -0.0004 | R4: =IF(M4<=5,"$0-$5",">$5") -> $0-$5 | S4: =IF(C4<=0.05,"$0-$0.05", IF(C4<=0.5,"$0.05-$0.5", IF(C4<=5,"$0.5-$5", IF(C4<=50,"$5-$50",">$50")))) -> >$50
A5: XRP | B5: XRP | C5: $2.12 | D5: 0.0055 | E5: =D5 -> 0.0055 | F5: =-D5 -> -0.0055 | G5: =D5 -> 0.0055 | H5: $125.42B | I5: $2,046,333,328 | J5: =IFERROR(VALUE(SUBSTITUTE(SUBSTITUTE(Table1[[#This Row],[Volume (24h) USD]],"$",""),",","")),0) -> 2046333328 | K5: 58.93B | L5: =IF(OR(LEFT(Table1[[#This Row],[Coin Name]],1)="A",LEFT(Table1[[#This Row],[Coin Name]],1)="E",LEFT(Table1[[#This Row],[Coin Name]],1)="I",LEFT(Table1[[#This Row],[Coin Name]],1)="O",LEFT(Table1[[#This Row],[Coin Name]],1)="U",LEFT(Table1[[#This Row],[Coin Name]],1)="B",LEFT(Table1[[#This Row],[Coin Name]],1)="C",LEFT(Table1[[#This Row],[Coin Name]],1)="D"),"Yes","No") -> No | M5: =VALUE(SUBSTITUTE(C5,"$","")) -> 2.12 | N5: =M5/(1+D5) -> 2.1084038 | O5: =IF(M5<10,"Up to $10",">= $10") -> Up to $10 | P5: =M5-N5 -> 0.011596221 | Q5: =F5 -> -0.0055 | R5: =IF(M5<=5,"$0-$5",">$5") -> $0-$5 | S5: =IF(C5<=0.05,"$0-$0.05", IF(C5<=0.5,"$0.05-$0.5", IF(C5<=5,"$0.5-$5", IF(C5<=50,"$5-$50",">$50")))) -> >$50
A6: USDC | B6: USDC | C6: $0.9998 | D6: 0.0003 | E6: =D6 -> 0.0003 | F6: =-D6 -> -0.0003 | G6: =D6 -> 0.0003 | H6: $61.23B | I6: $8,208,315,257 | J6: =IFERROR(VALUE(SUBSTITUTE(SUBSTITUTE(Table1[[#This Row],[Volume (24h) USD]],"$",""),",","")),0) -> 8208315257 | K6: 61.23B | L6: =IF(OR(LEFT(Table1[[#This Row],[Coin Name]],1)="A",LEFT(Table1[[#This Row],[Coin Name]],1)="E",LEFT(Table1[[#This Row],[Coin Name]],1)="I",LEFT(Table1[[#This Row],[Coin Name]],1)="O",LEFT(Table1[[#This Row],[Coin Name]],1)="U",LEFT(Table1[[#This Row],[Coin Name]],1)="B",LEFT(Table1[[#This Row],[Coin Name]],1)="C",LEFT(Table1[[#This Row],[Coin Name]],1)="D"),"Yes","No") -> Yes | M6: =VALUE(SUBSTITUTE(C6,"$","")) -> 0.9998 | N6: =M6/(1+D6) -> 0.99950015 | O6: =IF(M6<10,"Up to $10",">= $10") -> Up to $10 | P6: =M6-N6 -> 0.00029985004 | Q6: =F6 -> -0.0003 | R6: =IF(M6<=5,"$0-$5",">$5") -> $0-$5 | S6: =IF(M6<=0.05,"$0-$0.05",IF(M6<=0.5,"$0.05-$0.5",IF(M6<=5,"$0.5-$5",IF(M6<=50,"$5-$50",">$50")))) -> $0.5-$5
A7: Solana | B7: SOL | C7: $142.67 | D7: 0.0099 | E7: =D7 -> 0.0099 | F7: =-D7 -> -0.0099 | G7: =D7 -> 0.0099 | H7: $75.33B | I7: $2,904,341,748 | J7: =IFERROR(VALUE(SUBSTITUTE(SUBSTITUTE(Table1[[#This Row],[Volume (24h) USD]],"$",""),",","")),0) -> 2904341748 | K7: 527.96M | L7: =IF(OR(LEFT(Table1[[#This Row],[Coin Name]],1)="A",LEFT(Table1[[#This Row],[Coin Name]],1)="E",LEFT(Table1[[#This Row],[Coin Name]],1)="I",LEFT(Table1[[#This Row],[Coin Name]],1)="O",LEFT(Table1[[#This Row],[Coin Name]],1)="U",LEFT(Table1[[#This Row],[Coin Name]],1)="B",LEFT(Table1[[#This Row],[Coin Name]],1)="C",LEFT(Table1[[#This Row],[Coin Name]],1)="D"),"Yes","No") -> No | M7: =VALUE(SUBSTITUTE(C7,"$","")) -> 142.67 | N7: =M7/(1+D7) -> 141.27141 | O7: =IF(M7<10,"Up to $10",">= $10") -> >= $10 | P7: =M7-N7 -> 1.398587 | Q7: =F7 -> -0.0099 | R7: =IF(M7<=5,"$0-$5",">$5") -> >$5 | S7: =IF(C7<=0.05,"$0-$0.05", IF(C7<=0.5,"$0.05-$0.5", IF(C7<=5,"$0.5-$5", IF(C7<=50,"$5-$50",">$50")))) -> >$50
A8: BNB | B8: BNB | C8: $644.79 | D8: 0.001 | E8: =D8 -> 0.001 | F8: =-D8 -> -0.001 | G8: =D8 -> 0.001 | H8: $90.84B | I8: $1,497,928,447 | J8: =IFERROR(VALUE(SUBSTITUTE(SUBSTITUTE(Table1[[#This Row],[Volume (24h) USD]],"$",""),",","")),0) -> 1497928447 | K8: 140.88M | L8: =IF(OR(LEFT(Table1[[#This Row],[Coin Name]],1)="A",LEFT(Table1[[#This Row],[Coin Name]],1)="E",LEFT(Table1[[#This Row],[Coin Name]],1)="I",LEFT(Table1[[#This Row],[Coin Name]],1)="O",LEFT(Table1[[#This Row],[Coin Name]],1)="U",LEFT(Table1[[#This Row],[Coin Name]],1)="B",LEFT(Table1[[#This Row],[Coin Name]],1)="C",LEFT(Table1[[#This Row],[Coin Name]],1)="D"),"Yes","No") -> Yes | M8: =VALUE(SUBSTITUTE(C8,"$","")) -> 644.79 | N8: =M8/(1+D8) -> 644.14585 | O8: =IF(M8<10,"Up to $10",">= $10") -> >= $10 | P8: =M8-N8 -> 0.64414585 | Q8: =F8 -> -0.001 | R8: =IF(M8<=5,"$0-$5",">$5") -> >$5 | S8: =IF(M8<=0.05,"$0-$0.05",IF(M8<=0.5,"$0.05-$0.5",IF(M8<=5,"$0.5-$5",IF(M8<=50,"$5-$50",">$50")))) -> >$50
A9: TRON | B9: TRX | C9: $0.2734 | D9: 0.0036 | E9: =D9 -> 0.0036 | F9: =-D9 -> -0.0036 | G9: =D9 -> 0.0036 | H9: $25.93B | I9: $445,406,337 | J9: =IFERROR(VALUE(SUBSTITUTE(SUBSTITUTE(Table1[[#This Row],[Volume (24h) USD]],"$",""),",","")),0) -> 445406337 | K9: 94.82B | L9: =IF(OR(LEFT(Table1[[#This Row],[Coin Name]],1)="A",LEFT(Table1[[#This Row],[Coin Name]],1)="E",LEFT(Table1[[#This Row],[Coin Name]],1)="I",LEFT(Table1[[#This Row],[Coin Name]],1)="O",LEFT(Table1[[#This Row],[Coin Name]],1)="U",LEFT(Table1[[#This Row],[Coin Name]],1)="B",LEFT(Table1[[#This Row],[Coin Name]],1)="C",LEFT(Table1[[#This Row],[Coin Name]],1)="D"),"Yes","No") -> No | M9: =VALUE(SUBSTITUTE(C9,"$","")) -> 0.2734 | N9: =M9/(1+D9) -> 0.27241929 | O9: =IF(M9<10,"Up to $10",">= $10") -> Up to $10 | P9: =M9-N9 -> 0.00098070945 | Q9: =F9 -> -0.0036 | R9: =IF(M9<=5,"$0-$5",">$5") -> $0-$5 | S9: =IF(C9<=0.05,"$0-$0.05", IF(C9<=0.5,"$0.05-$0.5", IF(C9<=5,"$0.5-$5", IF(C9<=50,"$5-$50",">$50")))) -> >$50
A10: Dogecoin | B10: DOGE | C10: $0.1654 | D10: 0.0094 | E10: =D10 -> 0.0094 | F10: =-D10 -> -0.0094 | G10: =D10 -> 0.0094 | H10: $24.77B | I10: $781,433,558 | J10: =IFERROR(VALUE(SUBSTITUTE(SUBSTITUTE(Table1[[#This Row],[Volume (24h) USD]],"$",""),",","")),0) -> 781433558 | K10: 149.76B | L10: =IF(OR(LEFT(Table1[[#This Row],[Coin Name]],1)="A",LEFT(Table1[[#This Row],[Coin Name]],1)="E",LEFT(Table1[[#This Row],[Coin Name]],1)="I",LEFT(Table1[[#This Row],[Coin Name]],1)="O",LEFT(Table1[[#This Row],[Coin Name]],1)="U",LEFT(Table1[[#This Row],[Coin Name]],1)="B",LEFT(Table1[[#This Row],[Coin Name]],1)="C",LEFT(Table1[[#This Row],[Coin Name]],1)="D"),"Yes","No") -> Yes | M10: =VALUE(SUBSTITUTE(C10,"$","")) -> 0.1654 | N10: =M10/(1+D10) -> 0.16385972 | O10: =IF(M10<10,"Up to $10",">= $10") -> Up to $10 | P10: =M10-N10 -> 0.0015402814 | Q10: =F10 -> -0.0094 | R10: =IF(M10<=5,"$0-$5",">$5") -> $0-$5 | S10: =IF(M10<=0.05,"$0-$0.05",IF(M10<=0.5,"$0.05-$0.5",IF(M10<=5,"$0.5-$5",IF(M10<=50,"$5-$50",">$50")))) -> $0.05-$0.5
A11: Cardano | B11: ADA | C11: $0.5808 | D11: 0.0096 | E11: =D11 -> 0.0096 | F11: =-D11 -> -0.0096 | G11: =D11 -> 0.0096 | H11: $20.54B | I11: $539,447,597 | J11: =IFERROR(VALUE(SUBSTITUTE(SUBSTITUTE(Table1[[#This Row],[Volume (24h) USD]],"$",""),",","")),0) -> 539447597 | K11: 35.36B | L11: =IF(OR(LEFT(Table1[[#This Row],[Coin Name]],1)="A",LEFT(Table1[[#This Row],[Coin Name]],1)="E",LEFT(Table1[[#This Row],[Coin Name]],1)="I",LEFT(Table1[[#This Row],[Coin Name]],1)="O",LEFT(Table1[[#This Row],[Coin Name]],1)="U",LEFT(Table1[[#This Row],[Coin Name]],1)="B",LEFT(Table1[[#This Row],[Coin Name]],1)="C",LEFT(Table1[[#This Row],[Coin Name]],1)="D"),"Yes","No") -> Yes | M11: =VALUE(SUBSTITUTE(C11,"$","")) -> 0.5808 | N11: =M11/(1+D11) -> 0.57527734 | O11: =IF(M11<10,"Up to $10",">= $10") -> Up to $10 | P11: =M11-N11 -> 0.0055226624 | Q11: =F11 -> -0.0096 | R11: =IF(M11<=5,"$0-$5",">$5") -> $0-$5 | S11: =IF(M11<=0.05,"$0-$0.05",IF(M11<=0.5,"$0.05-$0.5",IF(M11<=5,"$0.5-$5",IF(M11<=50,"$5-$50",">$50")))) -> $0.5-$5
A12: Pudgy Penguins | B12: PENGU | C12: $0.009096 | D12: 0.014 | E12: =D12 -> 0.014 | F12: =-D12 -> -0.014 | G12: =D12 -> 0.014 | H12: $571.84M | I12: $60,468,868 | J12: =IFERROR(VALUE(SUBSTITUTE(SUBSTITUTE(Table1[[#This Row],[Volume (24h) USD]],"$",""),",","")),0) -> 60468868 | K12: 62.86B | L12: =IF(OR(LEFT(Table1[[#This Row],[Coin Name]],1)="A",LEFT(Table1[[#This Row],[Coin Name]],1)="E",LEFT(Table1[[#This Row],[Coin Name]],1)="I",LEFT(Table1[[#This Row],[Coin Name]],1)="O",LEFT(Table1[[#This Row],[Coin Name]],1)="U",LEFT(Table1[[#This Row],[Coin Name]],1)="B",LEFT(Table1[[#This Row],[Coin Name]],1)="C",LEFT(Table1[[#This Row],[Coin Name]],1)="D"),"Yes","No") -> No | M12: =VALUE(SUBSTITUTE(C12,"$","")) -> 0.009096 | N12: =M12/(1+D12) -> 0.0089704142 | O12: =IF(M12<10,"Up to $10",">= $10") -> Up to $10 | P12: =M12-N12 -> 0.0001255858 | Q12: =F12 -> -0.014 | R12: =IF(M12<=5,"$0-$5",">$5") -> $0-$5 | S12: =IF(C12<=0.05,"$0-$0.05", IF(C12<=0.5,"$0.05-$0.5", IF(C12<=5,"$0.5-$5", IF(C12<=50,"$5-$50",">$50")))) -> >$50
A13: Walrus | B13: WAL | C13: $0.4205 | D13: 0.0157 | E13: =D13 -> 0.0157 | F13: =-D13 -> -0.0157 | G13: =D13 -> 0.0157 | H13: $567M | I13: $22,854,744 | J13: =IFERROR(VALUE(SUBSTITUTE(SUBSTITUTE(Table1[[#This Row],[Volume (24h) USD]],"$",""),",","")),0) -> 22854744 | K13: 1.34B | L13: =IF(OR(LEFT(Table1[[#This Row],[Coin Name]],1)="A",LEFT(Table1[[#This Row],[Coin Name]],1)="E",LEFT(Table1[[#This Row],[Coin Name]],1)="I",LEFT(Table1[[#This Row],[Coin Name]],1)="O",LEFT(Table1[[#This Row],[Coin Name]],1)="U",LEFT(Table1[[#This Row],[Coin Name]],1)="B",LEFT(Table1[[#This Row],[Coin Name]],1)="C",LEFT(Table1[[#This Row],[Coin Name]],1)="D"),"Yes","No") -> No | M13: =VALUE(SUBSTITUTE(C13,"$","")) -> 0.4205 | N13: =M13/(1+D13) -> 0.4140002 | O13: =IF(M13<10,"Up to $10",">= $10") -> Up to $10 | P13: =M13-N13 -> 0.0064998031 | Q13: =F13 -> -0.0157 | R13: =IF(M13<=5,"$0-$5",">$5") -> $0-$5 | S13: =IF(C13<=0.05,"$0-$0.05", IF(C13<=0.5,"$0.05-$0.5", IF(C13<=5,"$0.5-$5", IF(C13<=50,"$5-$50",">$50")))) -> >$50
A14: Raydium | B14: RAY | C14: $2.06 | D14: 0.0117 | E14: =D14 -> 0.0117 | F14: =-D14 -> -0.0117 | G14: =D14 -> 0.0117 | H14: $551.36M | I14: $110,228,545 | J14: =IFERROR(VALUE(SUBSTITUTE(SUBSTITUTE(Table1[[#This Row],[Volume (24h) USD]],"$",""),",","")),0) -> 110228545 | K14: 267.62M | L14: =IF(OR(LEFT(Table1[[#This Row],[Coin Name]],1)="A",LEFT(Table1[[#This Row],[Coin Name]],1)="E",LEFT(Table1[[#This Row],[Coin Name]],1)="I",LEFT(Table1[[#This Row],[Coin Name]],1)="O",LEFT(Table1[[#This Row],[Coin Name]],1)="U",LEFT(Table1[[#This Row],[Coin Name]],1)="B",LEFT(Table1[[#This Row],[Coin Name]],1)="C",LEFT(Table1[[#This Row],[Coin Name]],1)="D"),"Yes","No") -> No | M14: =VALUE(SUBSTITUTE(C14,"$","")) -> 2.06 | N14: =M14/(1+D14) -> 2.0361767 | O14: =IF(M14<10,"Up to $10",">= $10") -> Up to $10 | P14: =M14-N14 -> 0.023823268 | Q14: =F14 -> -0.0117 | R14: =IF(M14<=5,"$0-$5",">$5") -> $0-$5 | S14: =IF(C14<=0.05,"$0-$0.05", IF(C14<=0.5,"$0.05-$0.5", IF(C14<=5,"$0.5-$5", IF(C14<=50,"$5-$50",">$50")))) -> >$50
A15: Orbiter Finance | B15: OBT | C15: $0.008376 | D15: 0.0427 | E15: =D15 -> 0.0427 | F15: =-D15 -> -0.0427 | G15: =D15 -> 0.0427 | H15: $25.97M | I15: $40,860,347 | J15: =IFERROR(VALUE(SUBSTITUTE(SUBSTITUTE(Table1[[#This Row],[Volume (24h) USD]],"$",""),",","")),0) -> 40860347 | K15: 3.1B | L15: =IF(OR(LEFT(Table1[[#This Row],[Coin Name]],1)="A",LEFT(Table1[[#This Row],[Coin Name]],1)="E",LEFT(Table1[[#This Row],[Coin Name]],1)="I",LEFT(Table1[[#This Row],[Coin Name]],1)="O",LEFT(Table1[[#This Row],[Coin Name]],1)="U",LEFT(Table1[[#This Row],[Coin Name]],1)="B",LEFT(Table1[[#This Row],[Coin Name]],1)="C",LEFT(Table1[[#This Row],[Coin Name]],1)="D"),"Yes","No") -> Yes | M15: =VALUE(SUBSTITUTE(C15,"$","")) -> 0.008376 | N15: =M15/(1+D15) -> 0.0080329913 | O15: =IF(M15<10,"Up to $10",">= $10") -> Up to $10 | P15: =M15-N15 -> 0.00034300873 | Q15: =F15 -> -0.0427 | R15: =IF(M15<=5,"$0-$5",">$5") -> $0-$5 | S15: =IF(M15<=0.05,"$0-$0.05",IF(M15<=0.5,"$0.05-$0.5",IF(M15<=5,"$0.5-$5",IF(M15<=50,"$5-$50",">$50")))) -> $0-$0.05
A16: Tezos | B16: XTZ | C16: $0.5207 | D16: 0.0066 | E16: =D16 -> 0.0066 | F16: =-D16 -> -0.0066 | G16: =D16 -> 0.0066 | H16: $545.72M | I16: $14,355,952 | J16: =IFERROR(VALUE(SUBSTITUTE(SUBSTITUTE(Table1[[#This Row],[Volume (24h) USD]],"$",""),",","")),0) -> 14355952 | K16: 1.04B | L16: =IF(OR(LEFT(Table1[[#This Row],[Coin Name]],1)="A",LEFT(Table1[[#This Row],[Coin Name]],1)="E",LEFT(Table1[[#This Row],[Coin Name]],1)="I",LEFT(Table1[[#This Row],[Coin Name]],1)="O",LEFT(Table1[[#This Row],[Coin Name]],1)="U",LEFT(Table1[[#This Row],[Coin Name]],1)="B",LEFT(Table1[[#This Row],[Coin Name]],1)="C",LEFT(Table1[[#This Row],[Coin Name]],1)="D"),"Yes","No") -> No | M16: =VALUE(SUBSTITUTE(C16,"$","")) -> 0.5207 | N16: =M16/(1+D16) -> 0.51728591 | O16: =IF(M16<10,"Up to $10",">= $10") -> Up to $10 | P16: =M16-N16 -> 0.003414087 | Q16: =F16 -> -0.0066 | R16: =IF(M16<=5,"$0-$5",">$5") -> $0-$5 | S16: =IF(C16<=0.05,"$0-$0.05", IF(C16<=0.5,"$0.05-$0.5", IF(C16<=5,"$0.5-$5", IF(C16<=50,"$5-$50",">$50")))) -> >$50
A17: Pyth Network | B17: PYTH | C17: $0.09453 | D17: 0.0227 | E17: =D17 -> 0.0227 | F17: =-D17 -> -0.0227 | G17: =D17 -> 0.0227 | H17: $543.57M | I17: $27,917,564 | J17: =IFERROR(VALUE(SUBSTITUTE(SUBSTITUTE(Table1[[#This Row],[Volume (24h) USD]],"$",""),",","")),0) -> 27917564 | K17: 5.74B | L17: =IF(OR(LEFT(Table1[[#This Row],[Coin Name]],1)="A",LEFT(Table1[[#This Row],[Coin Name]],1)="E",LEFT(Table1[[#This Row],[Coin Name]],1)="I",LEFT(Table1[[#This Row],[Coin Name]],1)="O",LEFT(Table1[[#This Row],[Coin Name]],1)="U",LEFT(Table1[[#This Row],[Coin Name]],1)="B",LEFT(Table1[[#This Row],[Coin Name]],1)="C",LEFT(Table1[[#This Row],[Coin Name]],1)="D"),"Yes","No") -> No | M17: =VALUE(SUBSTITUTE(C17,"$","")) -> 0.09453 | N17: =M17/(1+D17) -> 0.092431798 | O17: =IF(M17<10,"Up to $10",">= $10") -> Up to $10 | P17: =M17-N17 -> 0.0020982018 | Q17: =F17 -> -0.0227 | R17: =IF(M17<=5,"$0-$5",">$5") -> $0-$5 | S17: =IF(C17<=0.05,"$0-$0.05", IF(C17<=0.5,"$0.05-$0.5", IF(C17<=5,"$0.5-$5", IF(C17<=50,"$5-$50",">$50")))) -> >$50
A18: Flow | B18: FLOW | C18: $0.3394 | D18: 0.01 | E18: =D18 -> 0.01 | F18: =-D18 -> -0.01 | G18: =D18 -> 0.01 | H18: $539.91M | I18: $21,157,648 | J18: =IFERROR(VALUE(SUBSTITUTE(SUBSTITUTE(Table1[[#This Row],[Volume (24h) USD]],"$",""),",","")),0) -> 21157648 | K18: 1.59B | L18: =IF(OR(LEFT(Table1[[#This Row],[Coin Name]],1)="A",LEFT(Table1[[#This Row],[Coin Name]],1)="E",LEFT(Table1[[#This Row],[Coin Name]],1)="I",LEFT(Table1[[#This Row],[Coin Name]],1)="O",LEFT(Table1[[#This Row],[Coin Name]],1)="U",LEFT(Table1[[#This Row],[Coin Name]],1)="B",LEFT(Table1[[#This Row],[Coin Name]],1)="C",LEFT(Table1[[#This Row],[Coin Name]],1)="D"),"Yes","No") -> No | M18: =VALUE(SUBSTITUTE(C18,"$","")) -> 0.3394 | N18: =M18/(1+D18) -> 0.3360396 | O18: =IF(M18<10,"Up to $10",">= $10") -> Up to $10 | P18: =M18-N18 -> 0.003360396 | Q18: =F18 -> -0.01 | R18: =IF(M18<=5,"$0-$5",">$5") -> $0-$5 | S18: =IF(C18<=0.05,"$0-$0.05", IF(C18<=0.5,"$0.05-$0.5", IF(C18<=5,"$0.5-$5", IF(C18<=50,"$5-$50",">$50")))) -> >$50
A19: Maple Finance | B19: SYRUP | C19: $0.4626 | D19: 0.0305 | E19: =D19 -> 0.0305 | F19: =-D19 -> -0.0305 | G19: =D19 -> 0.0305 | H19: $515.17M | I19: $70,946,476 | J19: =IFERROR(VALUE(SUBSTITUTE(SUBSTITUTE(Table1[[#This Row],[Volume (24h) USD]],"$",""),",","")),0) -> 70946476 | K19: 1.11B | L19: =IF(OR(LEFT(Table1[[#This Row],[Coin Name]],1)="A",LEFT(Table1[[#This Row],[Coin Name]],1)="E",LEFT(Table1[[#This Row],[Coin Name]],1)="I",LEFT(Table1[[#This Row],[Coin Name]],1)="O",LEFT(Table1[[#This Row],[Coin Name]],1)="U",LEFT(Table1[[#This Row],[Coin Name]],1)="B",LEFT(Table1[[#This Row],[Coin Name]],1)="C",LEFT(Table1[[#This Row],[Coin Name]],1)="D"),"Yes","No") -> No | M19: =VALUE(SUBSTITUTE(C19,"$","")) -> 0.4626 | N19: =M19/(1+D19) -> 0.4489083 | O19: =IF(M19<10,"Up to $10",">= $10") -> Up to $10 | P19: =M19-N19 -> 0.013691703 | Q19: =F19 -> -0.0305 | R19: =IF(M19<=5,"$0-$5",">$5") -> $0-$5 | S19: =IF(C19<=0.05,"$0-$0.05", IF(C19<=0.5,"$0.05-$0.5", IF(C19<=5,"$0.5-$5", IF(C19<=50,"$5-$50",">$50")))) -> >$50
A20: Usual | B20: USUAL | C20: $0.07198 | D20: 0.0114 | E20: =D20 -> 0.0114 | F20: =-D20 -> -0.0114 | G20: =D20 -> 0.0114 | H20: $72.72M | I20: $25,758,134 | J20: =IFERROR(VALUE(SUBSTITUTE(SUBSTITUTE(Table1[[#This Row],[Volume (24h) USD]],"$",""),",","")),0) -> 25758134 | K20: 1.01B | L20: =IF(OR(LEFT(Table1[[#This Row],[Coin Name]],1)="A",LEFT(Table1[[#This Row],[Coin Name]],1)="E",LEFT(Table1[[#This Row],[Coin Name]],1)="I",LEFT(Table1[[#This Row],[Coin Name]],1)="O",LEFT(Table1[[#This Row],[Coin Name]],1)="U",LEFT(Table1[[#This Row],[Coin Name]],1)="B",LEFT(Table1[[#This Row],[Coin Name]],1)="C",LEFT(Table1[[#This Row],[Coin Name]],1)="D"),"Yes","No") -> Yes | M20: =VALUE(SUBSTITUTE(C20,"$","")) -> 0.07198 | N20: =M20/(1+D20) -> 0.071168677 | O20: =IF(M20<10,"Up to $10",">= $10") -> Up to $10 | P20: =M20-N20 -> 0.00081132292 | Q20: =F20 -> -0.0114 | R20: =IF(M20<=5,"$0-$5",">$5") -> $0-$5 | S20: =IF(M20<=0.05,"$0-$0.05",IF(M20<=0.5,"$0.05-$0.5",IF(M20<=5,"$0.5-$5",IF(M20<=50,"$5-$50",">$50")))) -> $0.05-$0.5
A21: TrueUSD | B21: TUSD | C21: $0.9976 | D21: 0.0001 | E21: =D21 -> 0.0001 | F21: =-D21 -> -0.0001 | G21: =D21 -> 0.0001 | H21: $493.33M | I21: $60,347,807 | J21: =IFERROR(VALUE(SUBSTITUTE(SUBSTITUTE(Table1[[#This Row],[Volume (24h) USD]],"$",""),",","")),0) -> 60347807 | K21: 494.51M | L21: =IF(OR(LEFT(Table1[[#This Row],[Coin Name]],1)="A",LEFT(Table1[[#This Row],[Coin Name]],1)="E",LEFT(Table1[[#This Row],[Coin Name]],1)="I",LEFT(Table1[[#This Row],[Coin Name]],1)="O",LEFT(Table1[[#This Row],[Coin Name]],1)="U",LEFT(Table1[[#This Row],[Coin Name]],1)="B",LEFT(Table1[[#This Row],[Coin Name]],1)="C",LEFT(Table1[[#This Row],[Coin Name]],1)="D"),"Yes","No") -> No | M21: =VALUE(SUBSTITUTE(C21,"$","")) -> 0.9976 | N21: =M21/(1+D21) -> 0.99750025 | O21: =IF(M21<10,"Up to $10",">= $10") -> Up to $10 | P21: =M21-N21 -> 9.9750025e-05 | Q21: =F21 -> -0.0001 | R21: =IF(M21<=5,"$0-$5",">$5") -> $0-$5 | S21: =IF(C21<=0.05,"$0-$0.05", IF(C21<=0.5,"$0.05-$0.5", IF(C21<=5,"$0.5-$5", IF(C21<=50,"$5-$50",">$50")))) -> >$50
A22: Fasttoken | B22: FTN | C22: $4.45 | D22: 0.0001 | E22: =D22 -> 0.0001 | F22: =-D22 -> -0.0001 | G22: =D22 -> 0.0001 | H22: $1.95B | I22: $58,305,626 | J22: =IFERROR(VALUE(SUBSTITUTE(SUBSTITUTE(Table1[[#This Row],[Volume (24h) USD]],"$",""),",","")),0) -> 58305626 | K22: 436.26M | L22: =IF(OR(LEFT(Table1[[#This Row],[Coin Name]],1)="A",LEFT(Table1[[#This Row],[Coin Name]],1)="E",LEFT(Table1[[#This Row],[Coin Name]],1)="I",LEFT(Table1[[#This Row],[Coin Name]],1)="O",LEFT(Table1[[#This Row],[Coin Name]],1)="U",LEFT(Table1[[#This Row],[Coin Name]],1)="B",LEFT(Table1[[#This Row],[Coin Name]],1)="C",LEFT(Table1[[#This Row],[Coin Name]],1)="D"),"Yes","No") -> No | M22: =VALUE(SUBSTITUTE(C22,"$","")) -> 4.45 | N22: =M22/(1+D22) -> 4.449555 | O22: =IF(M22<10,"Up to $10",">= $10") -> Up to $10 | P22: =M22-N22 -> 0.0004449555 | Q22: =F22 -> -0.0001 | R22: =IF(M22<=5,"$0-$5",">$5") -> $0-$5 | S22: =IF(C22<=0.05,"$0-$0.05", IF(C22<=0.5,"$0.05-$0.5", IF(C22<=5,"$0.5-$5", IF(C22<=50,"$5-$50",">$50")))) -> >$50
A23: Jupiter Perps LP | B23: JLP | C23: $4.32 | D23: 0.0045 | E23: =D23 -> 0.0045 | F23: =-D23 -> -0.0045 | G23: =D23 -> 0.0045 | H23: $1.49B | I23: $17,245,756 | J23: =IFERROR(VALUE(SUBSTITUTE(SUBSTITUTE(Table1[[#This Row],[Volume (24h) USD]],"$",""),",","")),0) -> 17245756 | K23: 343.49M | L23: =IF(OR(LEFT(Table1[[#This Row],[Coin Name]],1)="A",LEFT(Table1[[#This Row],[Coin Name]],1)="E",LEFT(Table1[[#This Row],[Coin Name]],1)="I",LEFT(Table1[[#This Row],[Coin Name]],1)="O",LEFT(Table1[[#This Row],[Coin Name]],1)="U",LEFT(Table1[[#This Row],[Coin Name]],1)="B",LEFT(Table1[[#This Row],[Coin Name]],1)="C",LEFT(Table1[[#This Row],[Coin Name]],1)="D"),"Yes","No") -> No | M23: =VALUE(SUBSTITUTE(C23,"$","")) -> 4.32 | N23: =M23/(1+D23) -> 4.3006471 | O23: =IF(M23<10,"Up to $10",">= $10") -> Up to $10 | P23: =M23-N23 -> 0.019352912 | Q23: =F23 -> -0.0045 | R23: =IF(M23<=5,"$0-$5",">$5") -> $0-$5 | S23: =IF(C23<=0.05,"$0-$0.05", IF(C23<=0.5,"$0.05-$0.5", IF(C23<=5,"$0.5-$5", IF(C23<=50,"$5-$50",">$50")))) -> >$50
A24: Zeebu | B24: ZBU | C24: $3.26 | D24: 0.0006 | E24: =D24 -> 0.0006 | F24: =-D24 -> -0.0006 | G24: =D24 -> 0.0006 | H24: $846.7M | I24: $486,945 | J24: =IFERROR(VALUE(SUBSTITUTE(SUBSTITUTE(Table1[[#This Row],[Volume (24h) USD]],"$",""),",","")),0) -> 486945 | K24: 258.97M | L24: =IF(OR(LEFT(Table1[[#This Row],[Coin Name]],1)="A",LEFT(Table1[[#This Row],[Coin Name]],1)="E",LEFT(Table1[[#This Row],[Coin Name]],1)="I",LEFT(Table1[[#This Row],[Coin Name]],1)="O",LEFT(Table1[[#This Row],[Coin Name]],1)="U",LEFT(Table1[[#This Row],[Coin Name]],1)="B",LEFT(Table1[[#This Row],[Coin Name]],1)="C",LEFT(Table1[[#This Row],[Coin Name]],1)="D"),"Yes","No") -> No | M24: =VALUE(SUBSTITUTE(C24,"$","")) -> 3.26 | N24: =M24/(1+D24) -> 3.2580452 | O24: =IF(M24<10,"Up to $10",">= $10") -> Up to $10 | P24: =M24-N24 -> 0.0019548271 | Q24: =F24 -> -0.0006 | R24: =IF(M24<=5,"$0-$5",">$5") -> $0-$5 | S24: =IF(C24<=0.05,"$0-$0.05", IF(C24<=0.5,"$0.05-$0.5", IF(C24<=5,"$0.5-$5", IF(C24<=50,"$5-$50",">$50")))) -> >$50
A25: Fellaz | B25: FLZ | C25: $1.43 | D25: 0.0052 | E25: =D25 -> 0.0052 | F25: =-D25 -> -0.0052 | G25: =D25 -> 0.0052 | H25: $677.19M | I25: $2,595,867 | J25: =IFERROR(VALUE(SUBSTITUTE(SUBSTITUTE(Table1[[#This Row],[Volume (24h) USD]],"$",""),",","")),0) -> 2595867 | K25: 471.87M | L25: =IF(OR(LEFT(Table1[[#This Row],[Coin Name]],1)="A",LEFT(Table1[[#This Row],[Coin Name]],1)="E",LEFT(Table1[[#This Row],[Coin Name]],1)="I",LEFT(Table1[[#This Row],[Coin Name]],1)="O",LEFT(Table1[[#This Row],[Coin Name]],1)="U",LEFT(Table1[[#This Row],[Coin Name]],1)="B",LEFT(Table1[[#This Row],[Coin Name]],1)="C",LEFT(Table1[[#This Row],[Coin Name]],1)="D"),"Yes","No") -> No | M25: =VALUE(SUBSTITUTE(C25,"$","")) -> 1.43 | N25: =M25/(1+D25) -> 1.4226025 | O25: =IF(M25<10,"Up to $10",">= $10") -> Up to $10 | P25: =M25-N25 -> 0.0073975328 | Q25: =F25 -> -0.0052 | R25: =IF(M25<=5,"$0-$5",">$5") -> $0-$5 | S25: =IF(C25<=0.05,"$0-$0.05", IF(C25<=0.5,"$0.05-$0.5", IF(C25<=5,"$0.5-$5", IF(C25<=50,"$5-$50",">$50")))) -> >$50
A26: Decentraland | B26: MANA | C26: $0.2505 | D26: 0.0137 | E26: =D26 -> 0.0137 | F26: =-D26 -> -0.0137 | G26: =D26 -> 0.0137 | H26: $493.58M | I26: $25,685,731 | J26: =IFERROR(VALUE(SUBSTITUTE(SUBSTITUTE(Table1[[#This Row],[Volume (24h) USD]],"$",""),",","")),0) -> 25685731 | K26: 1.96B | L26: =IF(OR(LEFT(Table1[[#This Row],[Coin Name]],1)="A",LEFT(Table1[[#This Row],[Coin Name]],1)="E",LEFT(Table1[[#This Row],[Coin Name]],1)="I",LEFT(Table1[[#This Row],[Coin Name]],1)="O",LEFT(Table1[[#This Row],[Coin Name]],1)="U",LEFT(Table1[[#This Row],[Coin Name]],1)="B",LEFT(Table1[[#This Row],[Coin Name]],1)="C",LEFT(Table1[[#This Row],[Coin Name]],1)="D"),"Yes","No") -> Yes | M26: =VALUE(SUBSTITUTE(C26,"$","")) -> 0.2505 | N26: =M26/(1+D26) -> 0.24711453 | O26: =IF(M26<10,"Up to $10",">= $10") -> Up to $10 | P26: =M26-N26 -> 0.0033854691 | Q26: =F26 -> -0.0137 | R26: =IF(M26<=5,"$0-$5",">$5") -> $0-$5 | S26: =IF(M26<=0.05,"$0-$0.05",IF(M26<=0.5,"$0.05-$0.5",IF(M26<=5,"$0.5-$5",IF(M26<=50,"$5-$50",">$50")))) -> $0.05-$0.5
A27: Eurite | B27: EURI | C27: $1.15 | D27: 0.0007 | E27: =D27 -> 0.0007 | F27: =-D27 -> -0.0007 | G27: =D27 -> 0.0007 | H27: $51.31M | I27: $22,680,605 | J27: =IFERROR(VALUE(SUBSTITUTE(SUBSTITUTE(Table1[[#This Row],[Volume (24h) USD]],"$",""),",","")),0) -> 22680605 | K27: 44.52M | L27: =IF(OR(LEFT(Table1[[#This Row],[Coin Name]],1)="A",LEFT(Table1[[#This Row],[Coin Name]],1)="E",LEFT(Table1[[#This Row],[Coin Name]],1)="I",LEFT(Table1[[#This Row],[Coin Name]],1)="O",LEFT(Table1[[#This Row],[Coin Name]],1)="U",LEFT(Table1[[#This Row],[Coin Name]],1)="B",LEFT(Table1[[#This Row],[Coin Name]],1)="C",LEFT(Table1[[#This Row],[Coin Name]],1)="D"),"Yes","No") -> Yes | M27: =VALUE(SUBSTITUTE(C27,"$","")) -> 1.15 | N27: =M27/(1+D27) -> 1.1491956 | O27: =IF(M27<10,"Up to $10",">= $10") -> Up to $10 | P27: =M27-N27 -> 0.00080443689 | Q27: =F27 -> -0.0007 | R27: =IF(M27<=5,"$0-$5",">$5") -> $0-$5 | S27: =IF(M27<=0.05,"$0-$0.05",IF(M27<=0.5,"$0.05-$0.5",IF(M27<=5,"$0.5-$5",IF(M27<=50,"$5-$50",">$50")))) -> $0.5-$5
A28: Falcon USD | B28: USDf | C28: $0.9997 | D28: 0 | E28: =D28 -> 0 | F28: =-D28 -> 0 | G28: =D28 -> 0 | H28: $563.5M | I28: $3,265,776 | J28: =IFERROR(VALUE(SUBSTITUTE(SUBSTITUTE(Table1[[#This Row],[Volume (24h) USD]],"$",""),",","")),0) -> 3265776 | K28: 563.65M | L28: =IF(OR(LEFT(Table1[[#This Row],[Coin Name]],1)="A",LEFT(Table1[[#This Row],[Coin Name]],1)="E",LEFT(Table1[[#This Row],[Coin Name]],1)="I",LEFT(Table1[[#This Row],[Coin Name]],1)="O",LEFT(Table1[[#This Row],[Coin Name]],1)="U",LEFT(Table1[[#This Row],[Coin Name]],1)="B",LEFT(Table1[[#This Row],[Coin Name]],1)="C",LEFT(Table1[[#This Row],[Coin Name]],1)="D"),"Yes","No") -> No | M28: =VALUE(SUBSTITUTE(C28,"$","")) -> 0.9997 | N28: =M28/(1+D28) -> 0.9997 | O28: =IF(M28<10,"Up to $10",">= $10") -> Up to $10 | P28: =M28-N28 -> 0 | Q28: =F28 -> 0 | R28: =IF(M28<=5,"$0-$5",">$5") -> $0-$5 | S28: =IF(C28<=0.05,"$0-$0.05", IF(C28<=0.5,"$0.05-$0.5", IF(C28<=5,"$0.5-$5", IF(C28<=50,"$5-$50",">$50")))) -> >$50
A29: Loaded Lions | B29: LION | C29: $0.01647 | D29: 0.0052 | E29: =D29 -> 0.0052 | F29: =-D29 -> -0.0052 | G29: =D29 -> 0.0052 | H29: $546.47M | I29: $183,208 | J29: =IFERROR(VALUE(SUBSTITUTE(SUBSTITUTE(Table1[[#This Row],[Volume (24h) USD]],"$",""),",","")),0) -> 183208 | K29: 33.16B | L29: =IF(OR(LEFT(Table1[[#This Row],[Coin Name]],1)="A",LEFT(Table1[[#This Row],[Coin Name]],1)="E",LEFT(Table1[[#This Row],[Coin Name]],1)="I",LEFT(Table1[[#This Row],[Coin Name]],1)="O",LEFT(Table1[[#This Row],[Coin Name]],1)="U",LEFT(Table1[[#This Row],[Coin Name]],1)="B",LEFT(Table1[[#This Row],[Coin Name]],1)="C",LEFT(Table1[[#This Row],[Coin Name]],1)="D"),"Yes","No") -> No | M29: =VALUE(SUBSTITUTE(C29,"$","")) -> 0.01647 | N29: =M29/(1+D29) -> 0.016384799 | O29: =IF(M29<10,"Up to $10",">= $10") -> Up to $10 | P29: =M29-N29 -> 8.5200955e-05 | Q29: =F29 -> -0.0052 | R29: =IF(M29<=5,"$0-$5",">$5") -> $0-$5 | S29: =IF(C29<=0.05,"$0-$0.05", IF(C29<=0.5,"$0.05-$0.5", IF(C29<=5,"$0.5-$5", IF(C29<=50,"$5-$50",">$50")))) -> >$50
A30: would | B30: WOULD | C30: $0.4946 | D30: 0.0303 | E30: =D30 -> 0.0303 | F30: =-D30 -> -0.0303 | G30: =D30 -> 0.0303 | H30: $494.41M | I30: $138,536 | J30: =IFERROR(VALUE(SUBSTITUTE(SUBSTITUTE(Table1[[#This Row],[Volume (24h) USD]],"$",""),",","")),0) -> 138536 | K30: 999.45M | L30: =IF(OR(LEFT(Table1[[#This Row],[Coin Name]],1)="A",LEFT(Table1[[#This Row],[Coin Name]],1)="E",LEFT(Table1[[#This Row],[Coin Name]],1)="I",LEFT(Table1[[#This Row],[Coin Name]],1)="O",LEFT(Table1[[#This Row],[Coin Name]],1)="U",LEFT(Table1[[#This Row],[Coin Name]],1)="B",LEFT(Table1[[#This Row],[Coin Name]],1)="C",LEFT(Table1[[#This Row],[Coin Name]],1)="D"),"Yes","No") -> No | M30: =VALUE(SUBSTITUTE(C30,"$","")) -> 0.4946 | N30: =M30/(1+D30) -> 0.48005435 | O30: =IF(M30<10,"Up to $10",">= $10") -> Up to $10 | P30: =M30-N30 -> 0.014545647 | Q30: =F30 -> -0.0303 | R30: =IF(M30<=5,"$0-$5",">$5") -> $0-$5 | S30: =IF(C30<=0.05,"$0-$0.05", IF(C30<=0.5,"$0.05-$0.5", IF(C30<=5,"$0.5-$5", IF(C30<=50,"$5-$50",">$50")))) -> >$50
A31: WhiteRock | B31: WHITE | C31: $0.0007355 | D31: 0.0066 | E31: =D31 -> 0.0066 | F31: =-D31 -> -0.0066 | G31: =D31 -> 0.0066 | H31: $478.12M | I31: $772,538 | J31: =IFERROR(VALUE(SUBSTITUTE(SUBSTITUTE(Table1[[#This Row],[Volume (24h) USD]],"$",""),",","")),0) -> 772538 | K31: 650B | L31: =IF(OR(LEFT(Table1[[#This Row],[Coin Name]],1)="A",LEFT(Table1[[#This Row],[Coin Name]],1)="E",LEFT(Table1[[#This Row],[Coin Name]],1)="I",LEFT(Table1[[#This Row],[Coin Name]],1)="O",LEFT(Table1[[#This Row],[Coin Name]],1)="U",LEFT(Table1[[#This Row],[Coin Name]],1)="B",LEFT(Table1[[#This Row],[Coin Name]],1)="C",LEFT(Table1[[#This Row],[Coin Name]],1)="D"),"Yes","No") -> No | M31: =VALUE(SUBSTITUTE(C31,"$","")) -> 0.0007355 | N31: =M31/(1+D31) -> 0.00073067753 | O31: =IF(M31<10,"Up to $10",">= $10") -> Up to $10 | P31: =M31-N31 -> 4.8224717e-06 | Q31: =F31 -> -0.0066 | R31: =IF(M31<=5,"$0-$5",">$5") -> $0-$5 | S31: =IF(C31<=0.05,"$0-$0.05", IF(C31<=0.5,"$0.05-$0.5", IF(C31<=5,"$0.5-$5", IF(C31<=50,"$5-$50",">$50")))) -> >$50
A32: Core | B32: CORE | C32: $0.5443 | D32: 0.0082 | E32: =D32 -> 0.0082 | F32: =-D32 -> -0.0082 | G32: =D32 -> 0.0082 | H32: $546.45M | I32: $14,386,742 | J32: =IFERROR(VALUE(SUBSTITUTE(SUBSTITUTE(Table1[[#This Row],[Volume (24h) USD]],"$",""),",","")),0) -> 14386742 | K32: 1B | L32: =IF(OR(LEFT(Table1[[#This Row],[Coin Name]],1)="A",LEFT(Table1[[#This Row],[Coin Name]],1)="E",LEFT(Table1[[#This Row],[Coin Name]],1)="I",LEFT(Table1[[#This Row],[Coin Name]],1)="O",LEFT(Table1[[#This Row],[Coin Name]],1)="U",LEFT(Table1[[#This Row],[Coin Name]],1)="B",LEFT(Table1[[#This Row],[Coin Name]],1)="C",LEFT(Table1[[#This Row],[Coin Name]],1)="D"),"Yes","No") -> Yes | M32: =VALUE(SUBSTITUTE(C32,"$","")) -> 0.5443 | N32: =M32/(1+D32) -> 0.53987304 | O32: =IF(M32<10,"Up to $10",">= $10") -> Up to $10 | P32: =M32-N32 -> 0.0044269589 | Q32: =F32 -> -0.0082 | R32: =IF(M32<=5,"$0-$5",">$5") -> $0-$5 | S32: =IF(M32<=0.05,"$0-$0.05",IF(M32<=0.5,"$0.05-$0.5",IF(M32<=5,"$0.5-$5",IF(M32<=50,"$5-$50",">$50")))) -> $0.5-$5
A33: Request | B33: REQ | C33: $0.1336 | D33: 0.0032 | E33: =D33 -> 0.0032 | F33: =-D33 -> -0.0032 | G33: =D33 -> 0.0032 | H33: $110.12M | I33: $3,268,919 | J33: =IFERROR(VALUE(SUBSTITUTE(SUBSTITUTE(Table1[[#This Row],[Volume (24h) USD]],"$",""),",","")),0) -> 3268919 | K33: 824.21M | L33: =IF(OR(LEFT(Table1[[#This Row],[Coin Name]],1)="A",LEFT(Table1[[#This Row],[Coin Name]],1)="E",LEFT(Table1[[#This Row],[Coin Name]],1)="I",LEFT(Table1[[#This Row],[Coin Name]],1)="O",LEFT(Table1[[#This Row],[Coin Name]],1)="U",LEFT(Table1[[#This Row],[Coin Name]],1)="B",LEFT(Table1[[#This Row],[Coin Name]],1)="C",LEFT(Table1[[#This Row],[Coin Name]],1)="D"),"Yes","No") -> No | M33: =VALUE(SUBSTITUTE(C33,"$","")) -> 0.1336 | N33: =M33/(1+D33) -> 0.13317384 | O33: =IF(M33<10,"Up to $10",">= $10") -> Up to $10 | P33: =M33-N33 -> 0.0004261563 | Q33: =F33 -> -0.0032 | R33: =IF(M33<=5,"$0-$5",">$5") -> $0-$5 | S33: =IF(C33<=0.05,"$0-$0.05", IF(C33<=0.5,"$0.05-$0.5", IF(C33<=5,"$0.5-$5", IF(C33<=50,"$5-$50",">$50")))) -> >$50
A34: Paycoin | B34: PCI | C34: $0.1043 | D34: 0.0063 | E34: =D34 -> 0.0063 | F34: =-D34 -> -0.0063 | G34: =D34 -> 0.0063 | H34: $109.85M | I34: $4,086,544 | J34: =IFERROR(VALUE(SUBSTITUTE(SUBSTITUTE(Table1[[#This Row],[Volume (24h) USD]],"$",""),",","")),0) -> 4086544 | K34: 1.05B | L34: =IF(OR(LEFT(Table1[[#This Row],[Coin Name]],1)="A",LEFT(Table1[[#This Row],[Coin Name]],1)="E",LEFT(Table1[[#This Row],[Coin Name]],1)="I",LEFT(Table1[[#This Row],[Coin Name]],1)="O",LEFT(Table1[[#This Row],[Coin Name]],1)="U",LEFT(Table1[[#This Row],[Coin Name]],1)="B",LEFT(Table1[[#This Row],[Coin Name]],1)="C",LEFT(Table1[[#This Row],[Coin Name]],1)="D"),"Yes","No") -> No | M34: =VALUE(SUBSTITUTE(C34,"$","")) -> 0.1043 | N34: =M34/(1+D34) -> 0.10364702 | O34: =IF(M34<10,"Up to $10",">= $10") -> Up to $10 | P34: =M34-N34 -> 0.00065297625 | Q34: =F34 -> -0.0063 | R34: =IF(M34<=5,"$0-$5",">$5") -> $0-$5 | S34: =IF(C34<=0.05,"$0-$0.05", IF(C34<=0.5,"$0.05-$0.5", IF(C34<=5,"$0.5-$5", IF(C34<=50,"$5-$50",">$50")))) -> >$50
A35: Aevo | B35: AEVO | C35: $0.07876 | D35: 0.0161 | E35: =D35 -> 0.0161 | F35: =-D35 -> -0.0161 | G35: =D35 -> 0.0161 | H35: $71.27M | I35: $12,716,009 | J35: =IFERROR(VALUE(SUBSTITUTE(SUBSTITUTE(Table1[[#This Row],[Volume (24h) USD]],"$",""),",","")),0) -> 12716009 | K35: 904.86M | L35: =IF(OR(LEFT(Table1[[#This Row],[Coin Name]],1)="A",LEFT(Table1[[#This Row],[Coin Name]],1)="E",LEFT(Table1[[#This Row],[Coin Name]],1)="I",LEFT(Table1[[#This Row],[Coin Name]],1)="O",LEFT(Table1[[#This Row],[Coin Name]],1)="U",LEFT(Table1[[#This Row],[Coin Name]],1)="B",LEFT(Table1[[#This Row],[Coin Name]],1)="C",LEFT(Table1[[#This Row],[Coin Name]],1)="D"),"Yes","No") -> Yes | M35: =VALUE(SUBSTITUTE(C35,"$","")) -> 0.07876 | N35: =M35/(1+D35) -> 0.077512056 | O35: =IF(M35<10,"Up to $10",">= $10") -> Up to $10 | P35: =M35-N35 -> 0.0012479441 | Q35: =F35 -> -0.0161 | R35: =IF(M35<=5,"$0-$5",">$5") -> $0-$5 | S35: =IF(M35<=0.05,"$0-$0.05",IF(M35<=0.5,"$0.05-$0.5",IF(M35<=5,"$0.5-$5",IF(M35<=50,"$5-$50",">$50")))) -> $0.05-$0.5
A36: Gravity (by Galxe) | B36: G | C36: $0.01148 | D36: 0.0113 | E36: =D36 -> 0.0113 | F36: =-D36 -> -0.0113 | G36: =D36 -> 0.0113 | H36: $109.13M | I36: $6,571,559 | J36: =IFERROR(VALUE(SUBSTITUTE(SUBSTITUTE(Table1[[#This Row],[Volume (24h) USD]],"$",""),",","")),0) -> 6571559 | K36: 9.5B | L36: =IF(OR(LEFT(Table1[[#This Row],[Coin Name]],1)="A",LEFT(Table1[[#This Row],[Coin Name]],1)="E",LEFT(Table1[[#This Row],[Coin Name]],1)="I",LEFT(Table1[[#This Row],[Coin Name]],1)="O",LEFT(Table1[[#This Row],[Coin Name]],1)="U",LEFT(Table1[[#This Row],[Coin Name]],1)="B",LEFT(Table1[[#This Row],[Coin Name]],1)="C",LEFT(Table1[[#This Row],[Coin Name]],1)="D"),"Yes","No") -> No | M36: =VALUE(SUBSTITUTE(C36,"$","")) -> 0.01148 | N36: =M36/(1+D36) -> 0.011351726 | O36: =IF(M36<10,"Up to $10",">= $10") -> Up to $10 | P36: =M36-N36 -> 0.0001282745 | Q36: =F36 -> -0.0113 | R36: =IF(M36<=5,"$0-$5",">$5") -> $0-$5 | S36: =IF(C36<=0.05,"$0-$0.05", IF(C36<=0.5,"$0.05-$0.5", IF(C36<=5,"$0.5-$5", IF(C36<=50,"$5-$50",">$50")))) -> >$50
A37: Terra | B37: LUNA | C37: $0.1536 | D37: 0.0101 | E37: =D37 -> 0.0101 | F37: =-D37 -> -0.0101 | G37: =D37 -> 0.0101 | H37: $109.06M | I37: $11,365,168 | J37: =IFERROR(VALUE(SUBSTITUTE(SUBSTITUTE(Table1[[#This Row],[Volume (24h) USD]],"$",""),",","")),0) -> 11365168 | K37: 709.98M | L37: =IF(OR(LEFT(Table1[[#This Row],[Coin Name]],1)="A",LEFT(Table1[[#This Row],[Coin Name]],1)="E",LEFT(Table1[[#This Row],[Coin Name]],1)="I",LEFT(Table1[[#This Row],[Coin Name]],1)="O",LEFT(Table1[[#This Row],[Coin Name]],1)="U",LEFT(Table1[[#This Row],[Coin Name]],1)="B",LEFT(Table1[[#This Row],[Coin Name]],1)="C",LEFT(Table1[[#This Row],[Coin Name]],1)="D"),"Yes","No") -> No | M37: =VALUE(SUBSTITUTE(C37,"$","")) -> 0.1536 | N37: =M37/(1+D37) -> 0.15206415 | O37: =IF(M37<10,"Up to $10",">= $10") -> Up to $10 | P37: =M37-N37 -> 0.0015358479 | Q37: =F37 -> -0.0101 | R37: =IF(M37<=5,"$0-$5",">$5") -> $0-$5 | S37: =IF(C37<=0.05,"$0-$0.05", IF(C37<=0.5,"$0.05-$0.5", IF(C37<=5,"$0.5-$5", IF(C37<=50,"$5-$50",">$50")))) -> >$50
A38: Solar | B38: SXP | C38: $0.1680 | D38: 0.0029 | E38: =D38 -> 0.0029 | F38: =-D38 -> -0.0029 | G38: =D38 -> 0.0029 | H38: $108.68M | I38: $44,129,611 | J38: =IFERROR(VALUE(SUBSTITUTE(SUBSTITUTE(Table1[[#This Row],[Volume (24h) USD]],"$",""),",","")),0) -> 44129611 | K38: 646.86M | L38: =IF(OR(LEFT(Table1[[#This Row],[Coin Name]],1)="A",LEFT(Table1[[#This Row],[Coin Name]],1)="E",LEFT(Table1[[#This Row],[Coin Name]],1)="I",LEFT(Table1[[#This Row],[Coin Name]],1)="O",LEFT(Table1[[#This Row],[Coin Name]],1)="U",LEFT(Table1[[#This Row],[Coin Name]],1)="B",LEFT(Table1[[#This Row],[Coin Name]],1)="C",LEFT(Table1[[#This Row],[Coin Name]],1)="D"),"Yes","No") -> No | M38: =VALUE(SUBSTITUTE(C38,"$","")) -> 0.168 | N38: =M38/(1+D38) -> 0.16751421 | O38: =IF(M38<10,"Up to $10",">= $10") -> Up to $10 | P38: =M38-N38 -> 0.00048579121 | Q38: =F38 -> -0.0029 | R38: =IF(M38<=5,"$0-$5",">$5") -> $0-$5 | S38: =IF(C38<=0.05,"$0-$0.05", IF(C38<=0.5,"$0.05-$0.5", IF(C38<=5,"$0.5-$5", IF(C38<=50,"$5-$50",">$50")))) -> >$50
A39: AI Companions | B39: AIC | C39: $0.09574 | D39: 0.0109 | E39: =D39 -> 0.0109 | F39: =-D39 -> -0.0109 | G39: =D39 -> 0.0109 | H39: $71.81M | I39: $9,190,572 | J39: =IFERROR(VALUE(SUBSTITUTE(SUBSTITUTE(Table1[[#This Row],[Volume (24h) USD]],"$",""),",","")),0) -> 9190572 | K39: 749.99M | L39: =IF(OR(LEFT(Table1[[#This Row],[Coin Name]],1)="A",LEFT(Table1[[#This Row],[Coin Name]],1)="E",LEFT(Table1[[#This Row],[Coin Name]],1)="I",LEFT(Table1[[#This Row],[Coin Name]],1)="O",LEFT(Table1[[#This Row],[Coin Name]],1)="U",LEFT(Table1[[#This Row],[Coin Name]],1)="B",LEFT(Table1[[#This Row],[Coin Name]],1)="C",LEFT(Table1[[#This Row],[Coin Name]],1)="D"),"Yes","No") -> Yes | M39: =VALUE(SUBSTITUTE(C39,"$","")) -> 0.09574 | N39: =M39/(1+D39) -> 0.094707686 | O39: =IF(M39<10,"Up to $10",">= $10") -> Up to $10 | P39: =M39-N39 -> 0.0010323138 | Q39: =F39 -> -0.0109 | R39: =IF(M39<=5,"$0-$5",">$5") -> $0-$5 | S39: =IF(M39<=0.05,"$0-$0.05",IF(M39<=0.5,"$0.05-$0.5",IF(M39<=5,"$0.5-$5",IF(M39<=50,"$5-$50",">$50")))) -> $0.05-$0.5
A40: World Mobile Token | B40: WMTX | C40: $0.1537 | D40: 0.0054 | E40: =D40 -> 0.0054 | F40: =-D40 -> -0.0054 | G40: =D40 -> 0.0054 | H40: $108.02M | I40: $7,215,924 | J40: =IFERROR(VALUE(SUBSTITUTE(SUBSTITUTE(Table1[[#This Row],[Volume (24h) USD]],"$",""),",","")),0) -> 7215924 | K40: 702.77M | L40: =IF(OR(LEFT(Table1[[#This Row],[Coin Name]],1)="A",LEFT(Table1[[#This Row],[Coin Name]],1)="E",LEFT(Table1[[#This Row],[Coin Name]],1)="I",LEFT(Table1[[#This Row],[Coin Name]],1)="O",LEFT(Table1[[#This Row],[Coin Name]],1)="U",LEFT(Table1[[#This Row],[Coin Name]],1)="B",LEFT(Table1[[#This Row],[Coin Name]],1)="C",LEFT(Table1[[#This Row],[Coin Name]],1)="D"),"Yes","No") -> No | M40: =VALUE(SUBSTITUTE(C40,"$","")) -> 0.1537 | N40: =M40/(1+D40) -> 0.15287448 | O40: =IF(M40<10,"Up to $10",">= $10") -> Up to $10 | P40: =M40-N40 -> 0.00082552218 | Q40: =F40 -> -0.0054 | R40: =IF(M40<=5,"$0-$5",">$5") -> $0-$5 | S40: =IF(C40<=0.05,"$0-$0.05", IF(C40<=0.5,"$0.05-$0.5", IF(C40<=5,"$0.5-$5", IF(C40<=50,"$5-$50",">$50")))) -> >$50
A41: SKALE | B41: SKL | C41: $0.01813 | D41: 0.0159 | E41: =D41 -> 0.0159 | F41: =-D41 -> -0.0159 | G41: =D41 -> 0.0159 | H41: $107.06M | I41: $8,143,928 | J41: =IFERROR(VALUE(SUBSTITUTE(SUBSTITUTE(Table1[[#This Row],[Volume (24h) USD]],"$",""),",","")),0) -> 8143928 | K41: 5.9B | L41: =IF(OR(LEFT(Table1[[#This Row],[Coin Name]],1)="A",LEFT(Table1[[#This Row],[Coin Name]],1)="E",LEFT(Table1[[#This Row],[Coin Name]],1)="I",LEFT(Table1[[#This Row],[Coin Name]],1)="O",LEFT(Table1[[#This Row],[Coin Name]],1)="U",LEFT(Table1[[#This Row],[Coin Name]],1)="B",LEFT(Table1[[#This Row],[Coin Name]],1)="C",LEFT(Table1[[#This Row],[Coin Name]],1)="D"),"Yes","No") -> No | M41: =VALUE(SUBSTITUTE(C41,"$","")) -> 0.01813 | N41: =M41/(1+D41) -> 0.017846245 | O41: =IF(M41<10,"Up to $10",">= $10") -> Up to $10 | P41: =M41-N41 -> 0.00028375529 | Q41: =F41 -> -0.0159 | R41: =IF(M41<=5,"$0-$5",">$5") -> $0-$5 | S41: =IF(C41<=0.05,"$0-$0.05", IF(C41<=0.5,"$0.05-$0.5", IF(C41<=5,"$0.5-$5", IF(C41<=50,"$5-$50",">$50")))) -> >$50
A42: Alaya Governance Token | B42: AGT | C42: $0.01390 | D42: 0.0055 | E42: =D42 -> 0.0055 | F42: =-D42 -> -0.0055 | G42: =D42 -> 0.0055 | H42: $19.47M | I42: $7,675,089 | J42: =IFERROR(VALUE(SUBSTITUTE(SUBSTITUTE(Table1[[#This Row],[Volume (24h) USD]],"$",""),",","")),0) -> 7675089 | K42: 1.4B | L42: =IF(OR(LEFT(Table1[[#This Row],[Coin Name]],1)="A",LEFT(Table1[[#This Row],[Coin Name]],1)="E",LEFT(Table1[[#This Row],[Coin Name]],1)="I",LEFT(Table1[[#This Row],[Coin Name]],1)="O",LEFT(Table1[[#This Row],[Coin Name]],1)="U",LEFT(Table1[[#This Row],[Coin Name]],1)="B",LEFT(Table1[[#This Row],[Coin Name]],1)="C",LEFT(Table1[[#This Row],[Coin Name]],1)="D"),"Yes","No") -> Yes | M42: =VALUE(SUBSTITUTE(C42,"$","")) -> 0.0139 | N42: =M42/(1+D42) -> 0.013823968 | O42: =IF(M42<10,"Up to $10",">= $10") -> Up to $10 | P42: =M42-N42 -> 7.6031825e-05 | Q42: =F42 -> -0.0055 | R42: =IF(M42<=5,"$0-$5",">$5") -> $0-$5 | S42: =IF(M42<=0.05,"$0-$0.05",IF(M42<=0.5,"$0.05-$0.5",IF(M42<=5,"$0.5-$5",IF(M42<=50,"$5-$50",">$50")))) -> $0-$0.05
A43: Degen | B43: DEGEN | C43: $0.003229 | D43: 0.0342 | E43: =D43 -> 0.0342 | F43: =-D43 -> -0.0342 | G43: =D43 -> 0.0342 | H43: $71.33M | I43: $7,399,528 | J43: =IFERROR(VALUE(SUBSTITUTE(SUBSTITUTE(Table1[[#This Row],[Volume (24h) USD]],"$",""),",","")),0) -> 7399528 | K43: 22.09B | L43: =IF(OR(LEFT(Table1[[#This Row],[Coin Name]],1)="A",LEFT(Table1[[#This Row],[Coin Name]],1)="E",LEFT(Table1[[#This Row],[Coin Name]],1)="I",LEFT(Table1[[#This Row],[Coin Name]],1)="O",LEFT(Table1[[#This Row],[Coin Name]],1)="U",LEFT(Table1[[#This Row],[Coin Name]],1)="B",LEFT(Table1[[#This Row],[Coin Name]],1)="C",LEFT(Table1[[#This Row],[Coin Name]],1)="D"),"Yes","No") -> Yes | M43: =VALUE(SUBSTITUTE(C43,"$","")) -> 0.003229 | N43: =M43/(1+D43) -> 0.0031222201 | O43: =IF(M43<10,"Up to $10",">= $10") -> Up to $10 | P43: =M43-N43 -> 0.00010677993 | Q43: =F43 -> -0.0342 | R43: =IF(M43<=5,"$0-$5",">$5") -> $0-$5 | S43: =IF(M43<=0.05,"$0-$0.05",IF(M43<=0.5,"$0.05-$0.5",IF(M43<=5,"$0.5-$5",IF(M43<=50,"$5-$50",">$50")))) -> $0-$0.05
A44: Memecoin | B44: MEME | C44: $0.001517 | D44: 0.0188 | E44: =D44 -> 0.0188 | F44: =-D44 -> -0.0188 | G44: =D44 -> 0.0188 | H44: $72.35M | I44: $15,717,380 | J44: =IFERROR(VALUE(SUBSTITUTE(SUBSTITUTE(Table1[[#This Row],[Volume (24h) USD]],"$",""),",","")),0) -> 15717380 | K44: 47.67B | L44: =IF(OR(LEFT(Table1[[#This Row],[Coin Name]],1)="A",LEFT(Table1[[#This Row],[Coin Name]],1)="E",LEFT(Table1[[#This Row],[Coin Name]],1)="I",LEFT(Table1[[#This Row],[Coin Name]],1)="O",LEFT(Table1[[#This Row],[Coin Name]],1)="U",LEFT(Table1[[#This Row],[Coin Name]],1)="B",LEFT(Table1[[#This Row],[Coin Name]],1)="C",LEFT(Table1[[#This Row],[Coin Name]],1)="D"),"Yes","No") -> No | M44: =VALUE(SUBSTITUTE(C44,"$","")) -> 0.001517 | N44: =M44/(1+D44) -> 0.0014890067 | O44: =IF(M44<10,"Up to $10",">= $10") -> Up to $10 | P44: =M44-N44 -> 2.7993325e-05 | Q44: =F44 -> -0.0188 | R44: =IF(M44<=5,"$0-$5",">$5") -> $0-$5 | S44: =IF(C44<=0.05,"$0-$0.05", IF(C44<=0.5,"$0.05-$0.5", IF(C44<=5,"$0.5-$5", IF(C44<=50,"$5-$50",">$50")))) -> >$50
A45: MiL.k | B45: MLK | C45: $0.1538 | D45: 0.0014 | E45: =D45 -> 0.0014 | F45: =-D45 -> -0.0014 | G45: =D45 -> 0.0014 | H45: $72.36M | I45: $4,873,644 | J45: =IFERROR(VALUE(SUBSTITUTE(SUBSTITUTE(Table1[[#This Row],[Volume (24h) USD]],"$",""),",","")),0) -> 4873644 | K45: 470.44M | L45: =IF(OR(LEFT(Table1[[#This Row],[Coin Name]],1)="A",LEFT(Table1[[#This Row],[Coin Name]],1)="E",LEFT(Table1[[#This Row],[Coin Name]],1)="I",LEFT(Table1[[#This Row],[Coin Name]],1)="O",LEFT(Table1[[#This Row],[Coin Name]],1)="U",LEFT(Table1[[#This Row],[Coin Name]],1)="B",LEFT(Table1[[#This Row],[Coin Name]],1)="C",LEFT(Table1[[#This Row],[Coin Name]],1)="D"),"Yes","No") -> No | M45: =VALUE(SUBSTITUTE(C45,"$","")) -> 0.1538 | N45: =M45/(1+D45) -> 0.15358498 | O45: =IF(M45<10,"Up to $10",">= $10") -> Up to $10 | P45: =M45-N45 -> 0.00021501897 | Q45: =F45 -> -0.0014 | R45: =IF(M45<=5,"$0-$5",">$5") -> $0-$5 | S45: =IF(C45<=0.05,"$0-$0.05", IF(C45<=0.5,"$0.05-$0.5", IF(C45<=5,"$0.5-$5", IF(C45<=50,"$5-$50",">$50")))) -> >$50
A46: Usual USD | B46: USD0 | C46: $0.9977 | D46: 0.0001 | E46: =D46 -> 0.0001 | F46: =-D46 -> -0.0001 | G46: =D46 -> 0.0001 | H46: $652.01M | I46: $6,754,108 | J46: =IFERROR(VALUE(SUBSTITUTE(SUBSTITUTE(Table1[[#This Row],[Volume (24h) USD]],"$",""),",","")),0) -> 6754108 | K46: 653.46M | L46: =IF(OR(LEFT(Table1[[#This Row],[Coin Name]],1)="A",LEFT(Table1[[#This Row],[Coin Name]],1)="E",LEFT(Table1[[#This Row],[Coin Name]],1)="I",LEFT(Table1[[#This Row],[Coin Name]],1)="O",LEFT(Table1[[#This Row],[Coin Name]],1)="U",LEFT(Table1[[#This Row],[Coin Name]],1)="B",LEFT(Table1[[#This Row],[Coin Name]],1)="C",LEFT(Table1[[#This Row],[Coin Name]],1)="D"),"Yes","No") -> Yes | M46: =VALUE(SUBSTITUTE(C46,"$","")) -> 0.9977 | N46: =M46/(1+D46) -> 0.99760024 | O46: =IF(M46<10,"Up to $10",">= $10") -> Up to $10 | P46: =M46-N46 -> 9.9760024e-05 | Q46: =F46 -> -0.0001 | R46: =IF(M46<=5,"$0-$5",">$5") -> $0-$5 | S46: =IF(M46<=0.05,"$0-$0.05",IF(M46<=0.5,"$0.05-$0.5",IF(M46<=5,"$0.5-$5",IF(M46<=50,"$5-$50",">$50")))) -> $0.5-$5
A47: COTI | B47: COTI | C47: $0.05028 | D47: 0.0095 | E47: =D47 -> 0.0095 | F47: =-D47 -> -0.0095 | G47: =D47 -> 0.0095 | H47: $109.59M | I47: $5,574,946 | J47: =IFERROR(VALUE(SUBSTITUTE(SUBSTITUTE(Table1[[#This Row],[Volume (24h) USD]],"$",""),",","")),0) -> 5574946 | K47: 2.17B | L47: =IF(OR(LEFT(Table1[[#This Row],[Coin Name]],1)="A",LEFT(Table1[[#This Row],[Coin Name]],1)="E",LEFT(Table1[[#This Row],[Coin Name]],1)="I",LEFT(Table1[[#This Row],[Coin Name]],1)="O",LEFT(Table1[[#This Row],[Coin Name]],1)="U",LEFT(Table1[[#This Row],[Coin Name]],1)="B",LEFT(Table1[[#This Row],[Coin Name]],1)="C",LEFT(Table1[[#This Row],[Coin Name]],1)="D"),"Yes","No") -> Yes | M47: =VALUE(SUBSTITUTE(C47,"$","")) -> 0.05028 | N47: =M47/(1+D47) -> 0.049806835 | O47: =IF(M47<10,"Up to $10",">= $10") -> Up to $10 | P47: =M47-N47 -> 0.00047316493 | Q47: =F47 -> -0.0095 | R47: =IF(M47<=5,"$0-$5",">$5") -> $0-$5 | S47: =IF(M47<=0.05,"$0-$0.05",IF(M47<=0.5,"$0.05-$0.5",IF(M47<=5,"$0.5-$5",IF(M47<=50,"$5-$50",">$50")))) -> $0.05-$0.5
A48: AVA (Travala) | B48: AVA | C48: $0.5361 | D48: 0.0049 | E48: =D48 -> 0.0049 | F48: =-D48 -> -0.0049 | G48: =D48 -> 0.0049 | H48: $36.9M | I48: $5,008,504 | J48: =IFERROR(VALUE(SUBSTITUTE(SUBSTITUTE(Table1[[#This Row],[Volume (24h) USD]],"$",""),",","")),0) -> 5008504 | K48: 68.83M | L48: =IF(OR(LEFT(Table1[[#This Row],[Coin Name]],1)="A",LEFT(Table1[[#This Row],[Coin Name]],1)="E",LEFT(Table1[[#This Row],[Coin Name]],1)="I",LEFT(Table1[[#This Row],[Coin Name]],1)="O",LEFT(Table1[[#This Row],[Coin Name]],1)="U",LEFT(Table1[[#This Row],[Coin Name]],1)="B",LEFT(Table1[[#This Row],[Coin Name]],1)="C",LEFT(Table1[[#This Row],[Coin Name]],1)="D"),"Yes","No") -> Yes | M48: =VALUE(SUBSTITUTE(C48,"$","")) -> 0.5361 | N48: =M48/(1+D48) -> 0.53348592 | O48: =IF(M48<10,"Up to $10",">= $10") -> Up to $10 | P48: =M48-N48 -> 0.002614081 | Q48: =F48 -> -0.0049 | R48: =IF(M48<=5,"$0-$5",">$5") -> $0-$5 | S48: =IF(M48<=0.05,"$0-$0.05",IF(M48<=0.5,"$0.05-$0.5",IF(M48<=5,"$0.5-$5",IF(M48<=50,"$5-$50",">$50")))) -> $0.5-$5
A49: Ontology | B49: ONT | C49: $0.1205 | D49: 0.0114 | E49: =D49 -> 0.0114 | F49: =-D49 -> -0.0114 | G49: =D49 -> 0.0114 | H49: $110.11M | I49: $4,884,866 | J49: =IFERROR(VALUE(SUBSTITUTE(SUBSTITUTE(Table1[[#This Row],[Volume (24h) USD]],"$",""),",","")),0) -> 4884866 | K49: 913.69M | L49: =IF(OR(LEFT(Table1[[#This Row],[Coin Name]],1)="A",LEFT(Table1[[#This Row],[Coin Name]],1)="E",LEFT(Table1[[#This Row],[Coin Name]],1)="I",LEFT(Table1[[#This Row],[Coin Name]],1)="O",LEFT(Table1[[#This Row],[Coin Name]],1)="U",LEFT(Table1[[#This Row],[Coin Name]],1)="B",LEFT(Table1[[#This Row],[Coin Name]],1)="C",LEFT(Table1[[#This Row],[Coin Name]],1)="D"),"Yes","No") -> Yes | M49: =VALUE(SUBSTITUTE(C49,"$","")) -> 0.1205 | N49: =M49/(1+D49) -> 0.11914178 | O49: =IF(M49<10,"Up to $10",">= $10") -> Up to $10 | P49: =M49-N49 -> 0.0013582163 | Q49: =F49 -> -0.0114 | R49: =IF(M49<=5,"$0-$5",">$5") -> $0-$5 | S49: =IF(M49<=0.05,"$0-$0.05",IF(M49<=0.5,"$0.05-$0.5",IF(M49<=5,"$0.5-$5",IF(M49<=50,"$5-$50",">$50")))) -> $0.05-$0.5
A50: Spark | B50: SPK | C50: $0.04205 | D50: 0.0244 | E50: =D50 -> 0.0244 | F50: =-D50 -> -0.0244 | G50: =D50 -> 0.0244 | H50: $71.5M | I50: $135,025,163 | J50: =IFERROR(VALUE(SUBSTITUTE(SUBSTITUTE(Table1[[#This Row],[Volume (24h) USD]],"$",""),",","")),0) -> 135025163 | K50: 1.7B | L50: =IF(OR(LEFT(Table1[[#This Row],[Coin Name]],1)="A",LEFT(Table1[[#This Row],[Coin Name]],1)="E",LEFT(Table1[[#This Row],[Coin Name]],1)="I",LEFT(Table1[[#This Row],[Coin Name]],1)="O",LEFT(Table1[[#This Row],[Coin Name]],1)="U",LEFT(Table1[[#This Row],[Coin Name]],1)="B",LEFT(Table1[[#This Row],[Coin Name]],1)="C",LEFT(Table1[[#This Row],[Coin Name]],1)="D"),"Yes","No") -> No | M50: =VALUE(SUBSTITUTE(C50,"$","")) -> 0.04205 | N50: =M50/(1+D50) -> 0.041048419 | O50: =IF(M50<10,"Up to $10",">= $10") -> Up to $10 | P50: =M50-N50 -> 0.0010015814 | Q50: =F50 -> -0.0244 | R50: =IF(M50<=5,"$0-$5",">$5") -> $0-$5 | S50: =IF(C50<=0.05,"$0-$0.05", IF(C50<=0.5,"$0.05-$0.5", IF(C50<=5,"$0.5-$5", IF(C50<=50,"$5-$50",">$50")))) -> >$50
A51: Global Commercial Business | B51: GCB | C51: $0.05947 | D51: 0.0002 | E51: =D51 -> 0.0002 | F51: =-D51 -> -0.0002 | G51: =D51 -> 0.0002 | H51: $71.47M | I51: $12,909 | J51: =IFERROR(VALUE(SUBSTITUTE(SUBSTITUTE(Table1[[#This Row],[Volume (24h) USD]],"$",""),",","")),0) -> 12909 | K51: 1.2B | L51: =IF(OR(LEFT(Table1[[#This Row],[Coin Name]],1)="A",LEFT(Table1[[#This Row],[Coin Name]],1)="E",LEFT(Table1[[#This Row],[Coin Name]],1)="I",LEFT(Table1[[#This Row],[Coin Name]],1)="O",LEFT(Table1[[#This Row],[Coin Name]],1)="U",LEFT(Table1[[#This Row],[Coin Name]],1)="B",LEFT(Table1[[#This Row],[Coin Name]],1)="C",LEFT(Table1[[#This Row],[Coin Name]],1)="D"),"Yes","No") -> No | M51: =VALUE(SUBSTITUTE(C51,"$","")) -> 0.05947 | N51: =M51/(1+D51) -> 0.059458108 | O51: =IF(M51<10,"Up to $10",">= $10") -> Up to $10 | P51: =M51-N51 -> 1.1891622e-05 | Q51: =F51 -> -0.0002 | R51: =IF(M51<=5,"$0-$5",">$5") -> $0-$5 | S51: =IF(C51<=0.05,"$0-$0.05", IF(C51<=0.5,"$0.05-$0.5", IF(C51<=5,"$0.5-$5", IF(C51<=50,"$5-$50",">$50")))) -> >$50
A52: NEM | B52: XEM | C52: $0.006272 | D52: 0.0053 | E52: =D52 -> 0.0053 | F52: =-D52 -> -0.0053 | G52: =D52 -> 0.0053 | H52: $56.45M | I52: $16,850,030 | J52: =IFERROR(VALUE(SUBSTITUTE(SUBSTITUTE(Table1[[#This Row],[Volume (24h) USD]],"$",""),",","")),0) -> 16850030 | K52: 8.99B | L52: =IF(OR(LEFT(Table1[[#This Row],[Coin Name]],1)="A",LEFT(Table1[[#This Row],[Coin Name]],1)="E",LEFT(Table1[[#This Row],[Coin Name]],1)="I",LEFT(Table1[[#This Row],[Coin Name]],1)="O",LEFT(Table1[[#This Row],[Coin Name]],1)="U",LEFT(Table1[[#This Row],[Coin Name]],1)="B",LEFT(Table1[[#This Row],[Coin Name]],1)="C",LEFT(Table1[[#This Row],[Coin Name]],1)="D"),"Yes","No") -> No | M52: =VALUE(SUBSTITUTE(C52,"$","")) -> 0.006272 | N52: =M52/(1+D52) -> 0.0062389337 | O52: =IF(M52<10,"Up to $10",">= $10") -> Up to $10 | P52: =M52-N52 -> 3.3066348e-05 | Q52: =F52 -> -0.0053 | R52: =IF(M52<=5,"$0-$5",">$5") -> $0-$5 | S52: =IF(C52<=0.05,"$0-$0.05", IF(C52<=0.5,"$0.05-$0.5", IF(C52<=5,"$0.5-$5", IF(C52<=50,"$5-$50",">$50")))) -> >$50
A53: Humans.ai | B53: HEART | C53: $0.006635 | D53: 0.0132 | E53: =D53 -> 0.0132 | F53: =-D53 -> -0.0132 | G53: =D53 -> 0.0132 | H53: $51.76M | I53: $448,016 | J53: =IFERROR(VALUE(SUBSTITUTE(SUBSTITUTE(Table1[[#This Row],[Volume (24h) USD]],"$",""),",","")),0) -> 448016 | K53: 7.8B | L53: =IF(OR(LEFT(Table1[[#This Row],[Coin Name]],1)="A",LEFT(Table1[[#This Row],[Coin Name]],1)="E",LEFT(Table1[[#This Row],[Coin Name]],1)="I",LEFT(Table1[[#This Row],[Coin Name]],1)="O",LEFT(Table1[[#This Row],[Coin Name]],1)="U",LEFT(Table1[[#This Row],[Coin Name]],1)="B",LEFT(Table1[[#This Row],[Coin Name]],1)="C",LEFT(Table1[[#This Row],[Coin Name]],1)="D"),"Yes","No") -> No | M53: =VALUE(SUBSTITUTE(C53,"$","")) -> 0.006635 | N53: =M53/(1+D53) -> 0.006548559 | O53: =IF(M53<10,"Up to $10",">= $10") -> Up to $10 | P53: =M53-N53 -> 8.6440979e-05 | Q53: =F53 -> -0.0132 | R53: =IF(M53<=5,"$0-$5",">$5") -> $0-$5 | S53: =IF(C53<=0.05,"$0-$0.05", IF(C53<=0.5,"$0.05-$0.5", IF(C53<=5,"$0.5-$5", IF(C53<=50,"$5-$50",">$50")))) -> >$50
A54: OMG Network | B54: OMG | C54: $0.1841 | D54: 0.0018 | E54: =D54 -> 0.0018 | F54: =-D54 -> -0.0018 | G54: =D54 -> 0.0018 | H54: $25.83M | I54: $3,675,488 | J54: =IFERROR(VALUE(SUBSTITUTE(SUBSTITUTE(Table1[[#This Row],[Volume (24h) USD]],"$",""),",","")),0) -> 3675488 | K54: 140.24M | L54: =IF(OR(LEFT(Table1[[#This Row],[Coin Name]],1)="A",LEFT(Table1[[#This Row],[Coin Name]],1)="E",LEFT(Table1[[#This Row],[Coin Name]],1)="I",LEFT(Table1[[#This Row],[Coin Name]],1)="O",LEFT(Table1[[#This Row],[Coin Name]],1)="U",LEFT(Table1[[#This Row],[Coin Name]],1)="B",LEFT(Table1[[#This Row],[Coin Name]],1)="C",LEFT(Table1[[#This Row],[Coin Name]],1)="D"),"Yes","No") -> Yes | M54: =VALUE(SUBSTITUTE(C54,"$","")) -> 0.1841 | N54: =M54/(1+D54) -> 0.18376922 | O54: =IF(M54<10,"Up to $10",">= $10") -> Up to $10 | P54: =M54-N54 -> 0.00033078459 | Q54: =F54 -> -0.0018 | R54: =IF(M54<=5,"$0-$5",">$5") -> $0-$5 | S54: =IF(M54<=0.05,"$0-$0.05",IF(M54<=0.5,"$0.05-$0.5",IF(M54<=5,"$0.5-$5",IF(M54<=50,"$5-$50",">$50")))) -> $0.05-$0.5
A55: Smooth Love Potion | B55: SLP | C55: $0.001253 | D55: 0.0153 | E55: =D55 -> 0.0153 | F55: =-D55 -> -0.0153 | G55: =D55 -> 0.0153 | H55: $51.48M | I55: $5,590,436 | J55: =IFERROR(VALUE(SUBSTITUTE(SUBSTITUTE(Table1[[#This Row],[Volume (24h) USD]],"$",""),",","")),0) -> 5590436 | K55: 41.08B | L55: =IF(OR(LEFT(Table1[[#This Row],[Coin Name]],1)="A",LEFT(Table1[[#This Row],[Coin Name]],1)="E",LEFT(Table1[[#This Row],[Coin Name]],1)="I",LEFT(Table1[[#This Row],[Coin Name]],1)="O",LEFT(Table1[[#This Row],[Coin Name]],1)="U",LEFT(Table1[[#This Row],[Coin Name]],1)="B",LEFT(Table1[[#This Row],[Coin Name]],1)="C",LEFT(Table1[[#This Row],[Coin Name]],1)="D"),"Yes","No") -> No | M55: =VALUE(SUBSTITUTE(C55,"$","")) -> 0.001253 | N55: =M55/(1+D55) -> 0.001234118 | O55: =IF(M55<10,"Up to $10",">= $10") -> Up to $10 | P55: =M55-N55 -> 1.8882005e-05 | Q55: =F55 -> -0.0153 | R55: =IF(M55<=5,"$0-$5",">$5") -> $0-$5 | S55: =IF(C55<=0.05,"$0-$0.05", IF(C55<=0.5,"$0.05-$0.5", IF(C55<=5,"$0.5-$5", IF(C55<=50,"$5-$50",">$50")))) -> >$50
A56: Neutron | B56: NTRN | C56: $0.08626 | D56: 0.0092 | E56: =D56 -> 0.0092 | F56: =-D56 -> -0.0092 | G56: =D56 -> 0.0092 | H56: $51.37M | I56: $2,536,218 | J56: =IFERROR(VALUE(SUBSTITUTE(SUBSTITUTE(Table1[[#This Row],[Volume (24h) USD]],"$",""),",","")),0) -> 2536218 | K56: 595.52M | L56: =IF(OR(LEFT(Table1[[#This Row],[Coin Name]],1)="A",LEFT(Table1[[#This Row],[Coin Name]],1)="E",LEFT(Table1[[#This Row],[Coin Name]],1)="I",LEFT(Table1[[#This Row],[Coin Name]],1)="O",LEFT(Table1[[#This Row],[Coin Name]],1)="U",LEFT(Table1[[#This Row],[Coin Name]],1)="B",LEFT(Table1[[#This Row],[Coin Name]],1)="C",LEFT(Table1[[#This Row],[Coin Name]],1)="D"),"Yes","No") -> No | M56: =VALUE(SUBSTITUTE(C56,"$","")) -> 0.08626 | N56: =M56/(1+D56) -> 0.085473642 | O56: =IF(M56<10,"Up to $10",">= $10") -> Up to $10 | P56: =M56-N56 -> 0.00078635751 | Q56: =F56 -> -0.0092 | R56: =IF(M56<=5,"$0-$5",">$5") -> $0-$5 | S56: =IF(C56<=0.05,"$0-$0.05", IF(C56<=0.5,"$0.05-$0.5", IF(C56<=5,"$0.5-$5", IF(C56<=50,"$5-$50",">$50")))) -> >$50
A57: Cortex | B57: CTXC | C57: $0.06667 | D57: 0.0011 | E57: =D57 -> 0.0011 | F57: =-D57 -> -0.0011 | G57: =D57 -> 0.0011 | H57: $15.36M | I57: $3,645,223 | J57: =IFERROR(VALUE(SUBSTITUTE(SUBSTITUTE(Table1[[#This Row],[Volume (24h) USD]],"$",""),",","")),0) -> 3645223 | K57: 230.41M | L57: =IF(OR(LEFT(Table1[[#This Row],[Coin Name]],1)="A",LEFT(Table1[[#This Row],[Coin Name]],1)="E",LEFT(Table1[[#This Row],[Coin Name]],1)="I",LEFT(Table1[[#This Row],[Coin Name]],1)="O",LEFT(Table1[[#This Row],[Coin Name]],1)="U",LEFT(Table1[[#This Row],[Coin Name]],1)="B",LEFT(Table1[[#This Row],[Coin Name]],1)="C",LEFT(Table1[[#This Row],[Coin Name]],1)="D"),"Yes","No") -> Yes | M57: =VALUE(SUBSTITUTE(C57,"$","")) -> 0.06667 | N57: =M57/(1+D57) -> 0.066596744 | O57: =IF(M57<10,"Up to $10",">= $10") -> Up to $10 | P57: =M57-N57 -> 7.3256418e-05 | Q57: =F57 -> -0.0011 | R57: =IF(M57<=5,"$0-$5",">$5") -> $0-$5 | S57: =IF(M57<=0.05,"$0-$0.05",IF(M57<=0.5,"$0.05-$0.5",IF(M57<=5,"$0.5-$5",IF(M57<=50,"$5-$50",">$50")))) -> $0.05-$0.5
A58: Ampleforth Governance Token | B58: FORTH | C58: $2.53 | D58: 0.0044 | E58: =D58 -> 0.0044 | F58: =-D58 -> -0.0044 | G58: =D58 -> 0.0044 | H58: $36.37M | I58: $2,914,375 | J58: =IFERROR(VALUE(SUBSTITUTE(SUBSTITUTE(Table1[[#This Row],[Volume (24h) USD]],"$",""),",","")),0) -> 2914375 | K58: 14.34M | L58: =IF(OR(LEFT(Table1[[#This Row],[Coin Name]],1)="A",LEFT(Table1[[#This Row],[Coin Name]],1)="E",LEFT(Table1[[#This Row],[Coin Name]],1)="I",LEFT(Table1[[#This Row],[Coin Name]],1)="O",LEFT(Table1[[#This Row],[Coin Name]],1)="U",LEFT(Table1[[#This Row],[Coin Name]],1)="B",LEFT(Table1[[#This Row],[Coin Name]],1)="C",LEFT(Table1[[#This Row],[Coin Name]],1)="D"),"Yes","No") -> Yes | M58: =VALUE(SUBSTITUTE(C58,"$","")) -> 2.53 | N58: =M58/(1+D58) -> 2.5189168 | O58: =IF(M58<10,"Up to $10",">= $10") -> Up to $10 | P58: =M58-N58 -> 0.011083234 | Q58: =F58 -> -0.0044 | R58: =IF(M58<=5,"$0-$5",">$5") -> $0-$5 | S58: =IF(M58<=0.05,"$0-$0.05",IF(M58<=0.5,"$0.05-$0.5",IF(M58<=5,"$0.5-$5",IF(M58<=50,"$5-$50",">$50")))) -> $0.5-$5
A59: GameBuild | B59: GAME | C59: $0.002875 | D59: 0.0045 | E59: =D59 -> 0.0045 | F59: =-D59 -> -0.0045 | G59: =D59 -> 0.0045 | H59: $50.98M | I59: $3,358,220 | J59: =IFERROR(VALUE(SUBSTITUTE(SUBSTITUTE(Table1[[#This Row],[Volume (24h) USD]],"$",""),",","")),0) -> 3358220 | K59: 17.72B | L59: =IF(OR(LEFT(Table1[[#This Row],[Coin Name]],1)="A",LEFT(Table1[[#This Row],[Coin Name]],1)="E",LEFT(Table1[[#This Row],[Coin Name]],1)="I",LEFT(Table1[[#This Row],[Coin Name]],1)="O",LEFT(Table1[[#This Row],[Coin Name]],1)="U",LEFT(Table1[[#This Row],[Coin Name]],1)="B",LEFT(Table1[[#This Row],[Coin Name]],1)="C",LEFT(Table1[[#This Row],[Coin Name]],1)="D"),"Yes","No") -> No | M59: =VALUE(SUBSTITUTE(C59,"$","")) -> 0.002875 | N59: =M59/(1+D59) -> 0.0028621205 | O59: =IF(M59<10,"Up to $10",">= $10") -> Up to $10 | P59: =M59-N59 -> 1.2879542e-05 | Q59: =F59 -> -0.0045 | R59: =IF(M59<=5,"$0-$5",">$5") -> $0-$5 | S59: =IF(C59<=0.05,"$0-$0.05", IF(C59<=0.5,"$0.05-$0.5", IF(C59<=5,"$0.5-$5", IF(C59<=50,"$5-$50",">$50")))) -> >$50
A60: Tornado Cash | B60: TORN | C60: $9.67 | D60: 0.001 | E60: =D60 -> 0.001 | F60: =-D60 -> -0.001 | G60: =D60 -> 0.001 | H60: $50.88M | I60: $101,491 | J60: =IFERROR(VALUE(SUBSTITUTE(SUBSTITUTE(Table1[[#This Row],[Volume (24h) USD]],"$",""),",","")),0) -> 101491 | K60: 5.26M | L60: =IF(OR(LEFT(Table1[[#This Row],[Coin Name]],1)="A",LEFT(Table1[[#This Row],[Coin Name]],1)="E",LEFT(Table1[[#This Row],[Coin Name]],1)="I",LEFT(Table1[[#This Row],[Coin Name]],1)="O",LEFT(Table1[[#This Row],[Coin Name]],1)="U",LEFT(Table1[[#This Row],[Coin Name]],1)="B",LEFT(Table1[[#This Row],[Coin Name]],1)="C",LEFT(Table1[[#This Row],[Coin Name]],1)="D"),"Yes","No") -> No | M60: =VALUE(SUBSTITUTE(C60,"$","")) -> 9.67 | N60: =M60/(1+D60) -> 9.6603397 | O60: =IF(M60<10,"Up to $10",">= $10") -> Up to $10 | P60: =M60-N60 -> 0.0096603397 | Q60: =F60 -> -0.001 | R60: =IF(M60<=5,"$0-$5",">$5") -> >$5 | S60: =IF(C60<=0.05,"$0-$0.05", IF(C60<=0.5,"$0.05-$0.5", IF(C60<=5,"$0.5-$5", IF(C60<=50,"$5-$50",">$50")))) -> >$50
A61: Contentos | B61: COS | C61: $0.002934 | D61: 0.0073 | E61: =D61 -> 0.0073 | F61: =-D61 -> -0.0073 | G61: =D61 -> 0.0073 | H61: $15.19M | I61: $2,771,456 | J61: =IFERROR(VALUE(SUBSTITUTE(SUBSTITUTE(Table1[[#This Row],[Volume (24h) USD]],"$",""),",","")),0) -> 2771456 | K61: 5.17B | L61: =IF(OR(LEFT(Table1[[#This Row],[Coin Name]],1)="A",LEFT(Table1[[#This Row],[Coin Name]],1)="E",LEFT(Table1[[#This Row],[Coin Name]],1)="I",LEFT(Table1[[#This Row],[Coin Name]],1)="O",LEFT(Table1[[#This Row],[Coin Name]],1)="U",LEFT(Table1[[#This Row],[Coin Name]],1)="B",LEFT(Table1[[#This Row],[Coin Name]],1)="C",LEFT(Table1[[#This Row],[Coin Name]],1)="D"),"Yes","No") -> Yes | M61: =VALUE(SUBSTITUTE(C61,"$","")) -> 0.002934 | N61: =M61/(1+D61) -> 0.002912737 | O61: =IF(M61<10,"Up to $10",">= $10") -> Up to $10 | P61: =M61-N61 -> 2.126298e-05 | Q61: =F61 -> -0.0073 | R61: =IF(M61<=5,"$0-$5",">$5") -> $0-$5 | S61: =IF(M61<=0.05,"$0-$0.05",IF(M61<=0.5,"$0.05-$0.5",IF(M61<=5,"$0.5-$5",IF(M61<=50,"$5-$50",">$50")))) -> $0-$0.05
A62: Kujira | B62: KUJI | C62: $0.3031 | D62: 0.0173 | E62: =D62 -> 0.0173 | F62: =-D62 -> -0.0173 | G62: =D62 -> 0.0173 | H62: $37.1M | I62: $17,173 | J62: =IFERROR(VALUE(SUBSTITUTE(SUBSTITUTE(Table1[[#This Row],[Volume (24h) USD]],"$",""),",","")),0) -> 17173 | K62: 122.34M | L62: =IF(OR(LEFT(Table1[[#This Row],[Coin Name]],1)="A",LEFT(Table1[[#This Row],[Coin Name]],1)="E",LEFT(Table1[[#This Row],[Coin Name]],1)="I",LEFT(Table1[[#This Row],[Coin Name]],1)="O",LEFT(Table1[[#This Row],[Coin Name]],1)="U",LEFT(Table1[[#This Row],[Coin Name]],1)="B",LEFT(Table1[[#This Row],[Coin Name]],1)="C",LEFT(Table1[[#This Row],[Coin Name]],1)="D"),"Yes","No") -> No | M62: =VALUE(SUBSTITUTE(C62,"$","")) -> 0.3031 | N62: =M62/(1+D62) -> 0.29794554 | O62: =IF(M62<10,"Up to $10",">= $10") -> Up to $10 | P62: =M62-N62 -> 0.0051544579 | Q62: =F62 -> -0.0173 | R62: =IF(M62<=5,"$0-$5",">$5") -> $0-$5 | S62: =IF(C62<=0.05,"$0-$0.05", IF(C62<=0.5,"$0.05-$0.5", IF(C62<=5,"$0.5-$5", IF(C62<=50,"$5-$50",">$50")))) -> >$50
A63: Gains Network | B63: GNS | C63: $1.26 | D63: 0.0031 | E63: =D63 -> 0.0031 | F63: =-D63 -> -0.0031 | G63: =D63 -> 0.0031 | H63: $36.94M | I63: $1,913,531 | J63: =IFERROR(VALUE(SUBSTITUTE(SUBSTITUTE(Table1[[#This Row],[Volume (24h) USD]],"$",""),",","")),0) -> 1913531 | K63: 29.27M | L63: =IF(OR(LEFT(Table1[[#This Row],[Coin Name]],1)="A",LEFT(Table1[[#This Row],[Coin Name]],1)="E",LEFT(Table1[[#This Row],[Coin Name]],1)="I",LEFT(Table1[[#This Row],[Coin Name]],1)="O",LEFT(Table1[[#This Row],[Coin Name]],1)="U",LEFT(Table1[[#This Row],[Coin Name]],1)="B",LEFT(Table1[[#This Row],[Coin Name]],1)="C",LEFT(Table1[[#This Row],[Coin Name]],1)="D"),"Yes","No") -> No | M63: =VALUE(SUBSTITUTE(C63,"$","")) -> 1.26 | N63: =M63/(1+D63) -> 1.2561061 | O63: =IF(M63<10,"Up to $10",">= $10") -> Up to $10 | P63: =M63-N63 -> 0.0038939288 | Q63: =F63 -> -0.0031 | R63: =IF(M63<=5,"$0-$5",">$5") -> $0-$5 | S63: =IF(C63<=0.05,"$0-$0.05", IF(C63<=0.5,"$0.05-$0.5", IF(C63<=5,"$0.5-$5", IF(C63<=50,"$5-$50",">$50")))) -> >$50
A64: DAR Open Network | B64: D | C64: $0.03010 | D64: 0.0158 | E64: =D64 -> 0.0158 | F64: =-D64 -> -0.0158 | G64: =D64 -> 0.0158 | H64: $19.51M | I64: $2,760,725 | J64: =IFERROR(VALUE(SUBSTITUTE(SUBSTITUTE(Table1[[#This Row],[Volume (24h) USD]],"$",""),",","")),0) -> 2760725 | K64: 647.87M | L64: =IF(OR(LEFT(Table1[[#This Row],[Coin Name]],1)="A",LEFT(Table1[[#This Row],[Coin Name]],1)="E",LEFT(Table1[[#This Row],[Coin Name]],1)="I",LEFT(Table1[[#This Row],[Coin Name]],1)="O",LEFT(Table1[[#This Row],[Coin Name]],1)="U",LEFT(Table1[[#This Row],[Coin Name]],1)="B",LEFT(Table1[[#This Row],[Coin Name]],1)="C",LEFT(Table1[[#This Row],[Coin Name]],1)="D"),"Yes","No") -> Yes | M64: =VALUE(SUBSTITUTE(C64,"$","")) -> 0.0301 | N64: =M64/(1+D64) -> 0.029631817 | O64: =IF(M64<10,"Up to $10",">= $10") -> Up to $10 | P64: =M64-N64 -> 0.00046818271 | Q64: =F64 -> -0.0158 | R64: =IF(M64<=5,"$0-$5",">$5") -> $0-$5 | S64: =IF(M64<=0.05,"$0-$0.05",IF(M64<=0.5,"$0.05-$0.5",IF(M64<=5,"$0.5-$5",IF(M64<=50,"$5-$50",">$50")))) -> $0-$0.05
A65: AirSwap | B65: AST | C65: $0.03958 | D65: 0.0197 | E65: =D65 -> 0.0197 | F65: =-D65 -> -0.0197 | G65: =D65 -> 0.0197 | H65: $6.91M | I65: $2,431,321 | J65: =IFERROR(VALUE(SUBSTITUTE(SUBSTITUTE(Table1[[#This Row],[Volume (24h) USD]],"$",""),",","")),0) -> 2431321 | K65: 174.47M | L65: =IF(OR(LEFT(Table1[[#This Row],[Coin Name]],1)="A",LEFT(Table1[[#This Row],[Coin Name]],1)="E",LEFT(Table1[[#This Row],[Coin Name]],1)="I",LEFT(Table1[[#This Row],[Coin Name]],1)="O",LEFT(Table1[[#This Row],[Coin Name]],1)="U",LEFT(Table1[[#This Row],[Coin Name]],1)="B",LEFT(Table1[[#This Row],[Coin Name]],1)="C",LEFT(Table1[[#This Row],[Coin Name]],1)="D"),"Yes","No") -> Yes | M65: =VALUE(SUBSTITUTE(C65,"$","")) -> 0.03958 | N65: =M65/(1+D65) -> 0.038815338 | O65: =IF(M65<10,"Up to $10",">= $10") -> Up to $10 | P65: =M65-N65 -> 0.00076466216 | Q65: =F65 -> -0.0197 | R65: =IF(M65<=5,"$0-$5",">$5") -> $0-$5 | S65: =IF(M65<=0.05,"$0-$0.05",IF(M65<=0.5,"$0.05-$0.5",IF(M65<=5,"$0.5-$5",IF(M65<=50,"$5-$50",">$50")))) -> $0-$0.05
A66: The Arena | B66: ARENA | C66: $0.01497 | D66: 0.0004 | E66: =D66 -> 0.0004 | F66: =-D66 -> -0.0004 | G66: =D66 -> 0.0004 | H66: $36.73M | I66: $260,802 | J66: =IFERROR(VALUE(SUBSTITUTE(SUBSTITUTE(Table1[[#This Row],[Volume (24h) USD]],"$",""),",","")),0) -> 260802 | K66: 2.45B | L66: =IF(OR(LEFT(Table1[[#This Row],[Coin Name]],1)="A",LEFT(Table1[[#This Row],[Coin Name]],1)="E",LEFT(Table1[[#This Row],[Coin Name]],1)="I",LEFT(Table1[[#This Row],[Coin Name]],1)="O",LEFT(Table1[[#This Row],[Coin Name]],1)="U",LEFT(Table1[[#This Row],[Coin Name]],1)="B",LEFT(Table1[[#This Row],[Coin Name]],1)="C",LEFT(Table1[[#This Row],[Coin Name]],1)="D"),"Yes","No") -> No | M66: =VALUE(SUBSTITUTE(C66,"$","")) -> 0.01497 | N66: =M66/(1+D66) -> 0.014964014 | O66: =IF(M66<10,"Up to $10",">= $10") -> Up to $10 | P66: =M66-N66 -> 5.9856058e-06 | Q66: =F66 -> -0.0004 | R66: =IF(M66<=5,"$0-$5",">$5") -> $0-$5 | S66: =IF(C66<=0.05,"$0-$0.05", IF(C66<=0.5,"$0.05-$0.5", IF(C66<=5,"$0.5-$5", IF(C66<=50,"$5-$50",">$50")))) -> >$50
A67: Ondo US Dollar Yield | B67: USDY | C67: $1.09 | D67: 0.0003 | E67: =D67 -> 0.0003 | F67: =-D67 -> -0.0003 | G67: =D67 -> 0.0003 | H67: $635.98M | I67: $2,293,702 | J67: =IFERROR(VALUE(SUBSTITUTE(SUBSTITUTE(Table1[[#This Row],[Volume (24h) USD]],"$",""),",","")),0) -> 2293702 | K67: 581.35M | L67: =IF(OR(LEFT(Table1[[#This Row],[Coin Name]],1)="A",LEFT(Table1[[#This Row],[Coin Name]],1)="E",LEFT(Table1[[#This Row],[Coin Name]],1)="I",LEFT(Table1[[#This Row],[Coin Name]],1)="O",LEFT(Table1[[#This Row],[Coin Name]],1)="U",LEFT(Table1[[#This Row],[Coin Name]],1)="B",LEFT(Table1[[#This Row],[Coin Name]],1)="C",LEFT(Table1[[#This Row],[Coin Name]],1)="D"),"Yes","No") -> Yes | M67: =VALUE(SUBSTITUTE(C67,"$","")) -> 1.09 | N67: =M67/(1+D67) -> 1.0896731 | O67: =IF(M67<10,"Up to $10",">= $10") -> Up to $10 | P67: =M67-N67 -> 0.00032690193 | Q67: =F67 -> -0.0003 | R67: =IF(M67<=5,"$0-$5",">$5") -> $0-$5 | S67: =IF(M67<=0.05,"$0-$0.05",IF(M67<=0.5,"$0.05-$0.5",IF(M67<=5,"$0.5-$5",IF(M67<=50,"$5-$50",">$50")))) -> $0.5-$5
A68: Covalent X Token | B68: CXT | C68: $0.02654 | D68: 0.0033 | E68: =D68 -> 0.0033 | F68: =-D68 -> -0.0033 | G68: =D68 -> 0.0033 | H68: $25.88M | I68: $2,231,412 | J68: =IFERROR(VALUE(SUBSTITUTE(SUBSTITUTE(Table1[[#This Row],[Volume (24h) USD]],"$",""),",","")),0) -> 2231412 | K68: 974.89M | L68: =IF(OR(LEFT(Table1[[#This Row],[Coin Name]],1)="A",LEFT(Table1[[#This Row],[Coin Name]],1)="E",LEFT(Table1[[#This Row],[Coin Name]],1)="I",LEFT(Table1[[#This Row],[Coin Name]],1)="O",LEFT(Table1[[#This Row],[Coin Name]],1)="U",LEFT(Table1[[#This Row],[Coin Name]],1)="B",LEFT(Table1[[#This Row],[Coin Name]],1)="C",LEFT(Table1[[#This Row],[Coin Name]],1)="D"),"Yes","No") -> Yes | M68: =VALUE(SUBSTITUTE(C68,"$","")) -> 0.02654 | N68: =M68/(1+D68) -> 0.026452706 | O68: =IF(M68<10,"Up to $10",">= $10") -> Up to $10 | P68: =M68-N68 -> 8.729393e-05 | Q68: =F68 -> -0.0033 | R68: =IF(M68<=5,"$0-$5",">$5") -> $0-$5 | S68: =IF(M68<=0.05,"$0-$0.05",IF(M68<=0.5,"$0.05-$0.5",IF(M68<=5,"$0.5-$5",IF(M68<=50,"$5-$50",">$50")))) -> $0-$0.05
A69: Metadium | B69: META | C69: $0.02100 | D69: 0.0008 | E69: =D69 -> 0.0008 | F69: =-D69 -> -0.0008 | G69: =D69 -> 0.0008 | H69: $35.98M | I69: $252,063 | J69: =IFERROR(VALUE(SUBSTITUTE(SUBSTITUTE(Table1[[#This Row],[Volume (24h) USD]],"$",""),",","")),0) -> 252063 | K69: 1.71B | L69: =IF(OR(LEFT(Table1[[#This Row],[Coin Name]],1)="A",LEFT(Table1[[#This Row],[Coin Name]],1)="E",LEFT(Table1[[#This Row],[Coin Name]],1)="I",LEFT(Table1[[#This Row],[Coin Name]],1)="O",LEFT(Table1[[#This Row],[Coin Name]],1)="U",LEFT(Table1[[#This Row],[Coin Name]],1)="B",LEFT(Table1[[#This Row],[Coin Name]],1)="C",LEFT(Table1[[#This Row],[Coin Name]],1)="D"),"Yes","No") -> No | M69: =VALUE(SUBSTITUTE(C69,"$","")) -> 0.021 | N69: =M69/(1+D69) -> 0.020983213 | O69: =IF(M69<10,"Up to $10",">= $10") -> Up to $10 | P69: =M69-N69 -> 1.6786571e-05 | Q69: =F69 -> -0.0008 | R69: =IF(M69<=5,"$0-$5",">$5") -> $0-$5 | S69: =IF(C69<=0.05,"$0-$0.05", IF(C69<=0.5,"$0.05-$0.5", IF(C69<=5,"$0.5-$5", IF(C69<=50,"$5-$50",">$50")))) -> >$50
A70: Shentu | B70: CTK | C70: $0.2442 | D70: 0.0032 | E70: =D70 -> 0.0032 | F70: =-D70 -> -0.0032 | G70: =D70 -> 0.0032 | H70: $35.96M | I70: $3,564,164 | J70: =IFERROR(VALUE(SUBSTITUTE(SUBSTITUTE(Table1[[#This Row],[Volume (24h) USD]],"$",""),",","")),0) -> 3564164 | K70: 147.24M | L70: =IF(OR(LEFT(Table1[[#This Row],[Coin Name]],1)="A",LEFT(Table1[[#This Row],[Coin Name]],1)="E",LEFT(Table1[[#This Row],[Coin Name]],1)="I",LEFT(Table1[[#This Row],[Coin Name]],1)="O",LEFT(Table1[[#This Row],[Coin Name]],1)="U",LEFT(Table1[[#This Row],[Coin Name]],1)="B",LEFT(Table1[[#This Row],[Coin Name]],1)="C",LEFT(Table1[[#This Row],[Coin Name]],1)="D"),"Yes","No") -> No | M70: =VALUE(SUBSTITUTE(C70,"$","")) -> 0.2442 | N70: =M70/(1+D70) -> 0.24342105 | O70: =IF(M70<10,"Up to $10",">= $10") -> Up to $10 | P70: =M70-N70 -> 0.00077894737 | Q70: =F70 -> -0.0032 | R70: =IF(M70<=5,"$0-$5",">$5") -> $0-$5 | S70: =IF(C70<=0.05,"$0-$0.05", IF(C70<=0.5,"$0.05-$0.5", IF(C70<=5,"$0.5-$5", IF(C70<=50,"$5-$50",">$50")))) -> >$50
A71: Nakamoto Games | B71: NAKA | C71: $0.3388 | D71: 0.0069 | E71: =D71 -> 0.0069 | F71: =-D71 -> -0.0069 | G71: =D71 -> 0.0069 | H71: $35.84M | I71: $8,693,511 | J71: =IFERROR(VALUE(SUBSTITUTE(SUBSTITUTE(Table1[[#This Row],[Volume (24h) USD]],"$",""),",","")),0) -> 8693511 | K71: 105.76M | L71: =IF(OR(LEFT(Table1[[#This Row],[Coin Name]],1)="A",LEFT(Table1[[#This Row],[Coin Name]],1)="E",LEFT(Table1[[#This Row],[Coin Name]],1)="I",LEFT(Table1[[#This Row],[Coin Name]],1)="O",LEFT(Table1[[#This Row],[Coin Name]],1)="U",LEFT(Table1[[#This Row],[Coin Name]],1)="B",LEFT(Table1[[#This Row],[Coin Name]],1)="C",LEFT(Table1[[#This Row],[Coin Name]],1)="D"),"Yes","No") -> No | M71: =VALUE(SUBSTITUTE(C71,"$","")) -> 0.3388 | N71: =M71/(1+D71) -> 0.3364783 | O71: =IF(M71<10,"Up to $10",">= $10") -> Up to $10 | P71: =M71-N71 -> 0.0023217003 | Q71: =F71 -> -0.0069 | R71: =IF(M71<=5,"$0-$5",">$5") -> $0-$5 | S71: =IF(C71<=0.05,"$0-$0.05", IF(C71<=0.5,"$0.05-$0.5", IF(C71<=5,"$0.5-$5", IF(C71<=50,"$5-$50",">$50")))) -> >$50
A72: Groestlcoin | B72: GRS | C72: $0.2993 | D72: 0.0015 | E72: =D72 -> 0.0015 | F72: =-D72 -> -0.0015 | G72: =D72 -> 0.0015 | H72: $26.28M | I72: $254,347 | J72: =IFERROR(VALUE(SUBSTITUTE(SUBSTITUTE(Table1[[#This Row],[Volume (24h) USD]],"$",""),",","")),0) -> 254347 | K72: 87.8M | L72: =IF(OR(LEFT(Table1[[#This Row],[Coin Name]],1)="A",LEFT(Table1[[#This Row],[Coin Name]],1)="E",LEFT(Table1[[#This Row],[Coin Name]],1)="I",LEFT(Table1[[#This Row],[Coin Name]],1)="O",LEFT(Table1[[#This Row],[Coin Name]],1)="U",LEFT(Table1[[#This Row],[Coin Name]],1)="B",LEFT(Table1[[#This Row],[Coin Name]],1)="C",LEFT(Table1[[#This Row],[Coin Name]],1)="D"),"Yes","No") -> No | M72: =VALUE(SUBSTITUTE(C72,"$","")) -> 0.2993 | N72: =M72/(1+D72) -> 0.29885172 | O72: =IF(M72<10,"Up to $10",">= $10") -> Up to $10 | P72: =M72-N72 -> 0.00044827758 | Q72: =F72 -> -0.0015 | R72: =IF(M72<=5,"$0-$5",">$5") -> $0-$5 | S72: =IF(C72<=0.05,"$0-$0.05", IF(C72<=0.5,"$0.05-$0.5", IF(C72<=5,"$0.5-$5", IF(C72<=50,"$5-$50",">$50")))) -> >$50
A73: Sui Name Service | B73: NS | C73: $0.1401 | D73: 0.0177 | E73: =D73 -> 0.0177 | F73: =-D73 -> -0.0177 | G73: =D73 -> 0.0177 | H73: $26.22M | I73: $2,161,326 | J73: =IFERROR(VALUE(SUBSTITUTE(SUBSTITUTE(Table1[[#This Row],[Volume (24h) USD]],"$",""),",","")),0) -> 2161326 | K73: 187.11M | L73: =IF(OR(LEFT(Table1[[#This Row],[Coin Name]],1)="A",LEFT(Table1[[#This Row],[Coin Name]],1)="E",LEFT(Table1[[#This Row],[Coin Name]],1)="I",LEFT(Table1[[#This Row],[Coin Name]],1)="O",LEFT(Table1[[#This Row],[Coin Name]],1)="U",LEFT(Table1[[#This Row],[Coin Name]],1)="B",LEFT(Table1[[#This Row],[Coin Name]],1)="C",LEFT(Table1[[#This Row],[Coin Name]],1)="D"),"Yes","No") -> No | M73: =VALUE(SUBSTITUTE(C73,"$","")) -> 0.1401 | N73: =M73/(1+D73) -> 0.13766336 | O73: =IF(M73<10,"Up to $10",">= $10") -> Up to $10 | P73: =M73-N73 -> 0.0024366414 | Q73: =F73 -> -0.0177 | R73: =IF(M73<=5,"$0-$5",">$5") -> $0-$5 | S73: =IF(C73<=0.05,"$0-$0.05", IF(C73<=0.5,"$0.05-$0.5", IF(C73<=5,"$0.5-$5", IF(C73<=50,"$5-$50",">$50")))) -> >$50
A74: Haedal Protocol | B74: HAEDAL | C74: $0.1279 | D74: 0.0076 | E74: =D74 -> 0.0076 | F74: =-D74 -> -0.0076 | G74: =D74 -> 0.0076 | H74: $26.07M | I74: $33,236,555 | J74: =IFERROR(VALUE(SUBSTITUTE(SUBSTITUTE(Table1[[#This Row],[Volume (24h) USD]],"$",""),",","")),0) -> 33236555 | K74: 203.75M | L74: =IF(OR(LEFT(Table1[[#This Row],[Coin Name]],1)="A",LEFT(Table1[[#This Row],[Coin Name]],1)="E",LEFT(Table1[[#This Row],[Coin Name]],1)="I",LEFT(Table1[[#This Row],[Coin Name]],1)="O",LEFT(Table1[[#This Row],[Coin Name]],1)="U",LEFT(Table1[[#This Row],[Coin Name]],1)="B",LEFT(Table1[[#This Row],[Coin Name]],1)="C",LEFT(Table1[[#This Row],[Coin Name]],1)="D"),"Yes","No") -> No | M74: =VALUE(SUBSTITUTE(C74,"$","")) -> 0.1279 | N74: =M74/(1+D74) -> 0.12693529 | O74: =IF(M74<10,"Up to $10",">= $10") -> Up to $10 | P74: =M74-N74 -> 0.00096470822 | Q74: =F74 -> -0.0076 | R74: =IF(M74<=5,"$0-$5",">$5") -> $0-$5 | S74: =IF(C74<=0.05,"$0-$0.05", IF(C74<=0.5,"$0.05-$0.5", IF(C74<=5,"$0.5-$5", IF(C74<=50,"$5-$50",">$50")))) -> >$50
A75: Fractal Bitcoin | B75: FB | C75: $0.5232 | D75: 0.0219 | E75: =D75 -> 0.0219 | F75: =-D75 -> -0.0219 | G75: =D75 -> 0.0219 | H75: $26.15M | I75: $5,485,485 | J75: =IFERROR(VALUE(SUBSTITUTE(SUBSTITUTE(Table1[[#This Row],[Volume (24h) USD]],"$",""),",","")),0) -> 5485485 | K75: 49.97M | L75: =IF(OR(LEFT(Table1[[#This Row],[Coin Name]],1)="A",LEFT(Table1[[#This Row],[Coin Name]],1)="E",LEFT(Table1[[#This Row],[Coin Name]],1)="I",LEFT(Table1[[#This Row],[Coin Name]],1)="O",LEFT(Table1[[#This Row],[Coin Name]],1)="U",LEFT(Table1[[#This Row],[Coin Name]],1)="B",LEFT(Table1[[#This Row],[Coin Name]],1)="C",LEFT(Table1[[#This Row],[Coin Name]],1)="D"),"Yes","No") -> No | M75: =VALUE(SUBSTITUTE(C75,"$","")) -> 0.5232 | N75: =M75/(1+D75) -> 0.51198747 | O75: =IF(M75<10,"Up to $10",">= $10") -> Up to $10 | P75: =M75-N75 -> 0.011212526 | Q75: =F75 -> -0.0219 | R75: =IF(M75<=5,"$0-$5",">$5") -> $0-$5 | S75: =IF(C75<=0.05,"$0-$0.05", IF(C75<=0.5,"$0.05-$0.5", IF(C75<=5,"$0.5-$5", IF(C75<=50,"$5-$50",">$50")))) -> >$50
A76: PlatON | B76: LAT | C76: $0.003926 | D76: 0.0094 | E76: =D76 -> 0.0094 | F76: =-D76 -> -0.0094 | G76: =D76 -> 0.0094 | H76: $25.94M | I76: $4,157,460 | J76: =IFERROR(VALUE(SUBSTITUTE(SUBSTITUTE(Table1[[#This Row],[Volume (24h) USD]],"$",""),",","")),0) -> 4157460 | K76: 6.6B | L76: =IF(OR(LEFT(Table1[[#This Row],[Coin Name]],1)="A",LEFT(Table1[[#This Row],[Coin Name]],1)="E",LEFT(Table1[[#This Row],[Coin Name]],1)="I",LEFT(Table1[[#This Row],[Coin Name]],1)="O",LEFT(Table1[[#This Row],[Coin Name]],1)="U",LEFT(Table1[[#This Row],[Coin Name]],1)="B",LEFT(Table1[[#This Row],[Coin Name]],1)="C",LEFT(Table1[[#This Row],[Coin Name]],1)="D"),"Yes","No") -> No | M76: =VALUE(SUBSTITUTE(C76,"$","")) -> 0.003926 | N76: =M76/(1+D76) -> 0.0038894393 | O76: =IF(M76<10,"Up to $10",">= $10") -> Up to $10 | P76: =M76-N76 -> 3.6560729e-05 | Q76: =F76 -> -0.0094 | R76: =IF(M76<=5,"$0-$5",">$5") -> $0-$5 | S76: =IF(C76<=0.05,"$0-$0.05", IF(C76<=0.5,"$0.05-$0.5", IF(C76<=5,"$0.5-$5", IF(C76<=50,"$5-$50",">$50")))) -> >$50
A77: NFPrompt | B77: NFP | C77: $0.05651 | D77: 0.0146 | E77: =D77 -> 0.0146 | F77: =-D77 -> -0.0146 | G77: =D77 -> 0.0146 | H77: $25.85M | I77: $3,148,017 | J77: =IFERROR(VALUE(SUBSTITUTE(SUBSTITUTE(Table1[[#This Row],[Volume (24h) USD]],"$",""),",","")),0) -> 3148017 | K77: 457.31M | L77: =IF(OR(LEFT(Table1[[#This Row],[Coin Name]],1)="A",LEFT(Table1[[#This Row],[Coin Name]],1)="E",LEFT(Table1[[#This Row],[Coin Name]],1)="I",LEFT(Table1[[#This Row],[Coin Name]],1)="O",LEFT(Table1[[#This Row],[Coin Name]],1)="U",LEFT(Table1[[#This Row],[Coin Name]],1)="B",LEFT(Table1[[#This Row],[Coin Name]],1)="C",LEFT(Table1[[#This Row],[Coin Name]],1)="D"),"Yes","No") -> No | M77: =VALUE(SUBSTITUTE(C77,"$","")) -> 0.05651 | N77: =M77/(1+D77) -> 0.055696826 | O77: =IF(M77<10,"Up to $10",">= $10") -> Up to $10 | P77: =M77-N77 -> 0.00081317366 | Q77: =F77 -> -0.0146 | R77: =IF(M77<=5,"$0-$5",">$5") -> $0-$5 | S77: =IF(C77<=0.05,"$0-$0.05", IF(C77<=0.5,"$0.05-$0.5", IF(C77<=5,"$0.5-$5", IF(C77<=50,"$5-$50",">$50")))) -> >$50
A78: Definitive | B78: EDGE | C78: $0.07508 | D78: 0.0007 | E78: =D78 -> 0.0007 | F78: =-D78 -> -0.0007 | G78: =D78 -> 0.0007 | H78: $15.25M | I78: $1,739,142 | J78: =IFERROR(VALUE(SUBSTITUTE(SUBSTITUTE(Table1[[#This Row],[Volume (24h) USD]],"$",""),",","")),0) -> 1739142 | K78: 203.02M | L78: =IF(OR(LEFT(Table1[[#This Row],[Coin Name]],1)="A",LEFT(Table1[[#This Row],[Coin Name]],1)="E",LEFT(Table1[[#This Row],[Coin Name]],1)="I",LEFT(Table1[[#This Row],[Coin Name]],1)="O",LEFT(Table1[[#This Row],[Coin Name]],1)="U",LEFT(Table1[[#This Row],[Coin Name]],1)="B",LEFT(Table1[[#This Row],[Coin Name]],1)="C",LEFT(Table1[[#This Row],[Coin Name]],1)="D"),"Yes","No") -> Yes | M78: =VALUE(SUBSTITUTE(C78,"$","")) -> 0.07508 | N78: =M78/(1+D78) -> 0.075027481 | O78: =IF(M78<10,"Up to $10",">= $10") -> Up to $10 | P78: =M78-N78 -> 5.2519237e-05 | Q78: =F78 -> -0.0007 | R78: =IF(M78<=5,"$0-$5",">$5") -> $0-$5 | S78: =IF(M78<=0.05,"$0-$0.05",IF(M78<=0.5,"$0.05-$0.5",IF(M78<=5,"$0.5-$5",IF(M78<=50,"$5-$50",">$50")))) -> $0.05-$0.5
A79: Alon | B79: ALON | C79: $0.01163 | D79: 0.0042 | E79: =D79 -> 0.0042 | F79: =-D79 -> -0.0042 | G79: =D79 -> 0.0042 | H79: $11.61M | I79: $1,737,116 | J79: =IFERROR(VALUE(SUBSTITUTE(SUBSTITUTE(Table1[[#This Row],[Volume (24h) USD]],"$",""),",","")),0) -> 1737116 | K79: 997.96M | L79: =IF(OR(LEFT(Table1[[#This Row],[Coin Name]],1)="A",LEFT(Table1[[#This Row],[Coin Name]],1)="E",LEFT(Table1[[#This Row],[Coin Name]],1)="I",LEFT(Table1[[#This Row],[Coin Name]],1)="O",LEFT(Table1[[#This Row],[Coin Name]],1)="U",LEFT(Table1[[#This Row],[Coin Name]],1)="B",LEFT(Table1[[#This Row],[Coin Name]],1)="C",LEFT(Table1[[#This Row],[Coin Name]],1)="D"),"Yes","No") -> Yes | M79: =VALUE(SUBSTITUTE(C79,"$","")) -> 0.01163 | N79: =M79/(1+D79) -> 0.011581358 | O79: =IF(M79<10,"Up to $10",">= $10") -> Up to $10 | P79: =M79-N79 -> 4.8641705e-05 | Q79: =F79 -> -0.0042 | R79: =IF(M79<=5,"$0-$5",">$5") -> $0-$5 | S79: =IF(M79<=0.05,"$0-$0.05",IF(M79<=0.5,"$0.05-$0.5",IF(M79<=5,"$0.5-$5",IF(M79<=50,"$5-$50",">$50")))) -> $0-$0.05
A80: DEAPcoin | B80: DEP | C80: $0.001245 | D80: 0.0025 | E80: =D80 -> 0.0025 | F80: =-D80 -> -0.0025 | G80: =D80 -> 0.0025 | H80: $36.78M | I80: $1,669,915 | J80: =IFERROR(VALUE(SUBSTITUTE(SUBSTITUTE(Table1[[#This Row],[Volume (24h) USD]],"$",""),",","")),0) -> 1669915 | K80: 29.54B | L80: =IF(OR(LEFT(Table1[[#This Row],[Coin Name]],1)="A",LEFT(Table1[[#This Row],[Coin Name]],1)="E",LEFT(Table1[[#This Row],[Coin Name]],1)="I",LEFT(Table1[[#This Row],[Coin Name]],1)="O",LEFT(Table1[[#This Row],[Coin Name]],1)="U",LEFT(Table1[[#This Row],[Coin Name]],1)="B",LEFT(Table1[[#This Row],[Coin Name]],1)="C",LEFT(Table1[[#This Row],[Coin Name]],1)="D"),"Yes","No") -> Yes | M80: =VALUE(SUBSTITUTE(C80,"$","")) -> 0.001245 | N80: =M80/(1+D80) -> 0.0012418953 | O80: =IF(M80<10,"Up to $10",">= $10") -> Up to $10 | P80: =M80-N80 -> 3.1047382e-06 | Q80: =F80 -> -0.0025 | R80: =IF(M80<=5,"$0-$5",">$5") -> $0-$5 | S80: =IF(M80<=0.05,"$0-$0.05",IF(M80<=0.5,"$0.05-$0.5",IF(M80<=5,"$0.5-$5",IF(M80<=50,"$5-$50",">$50")))) -> $0-$0.05
A81: Radiant Capital | B81: RDNT | C81: $0.02085 | D81: 0.0126 | E81: =D81 -> 0.0126 | F81: =-D81 -> -0.0126 | G81: =D81 -> 0.0126 | H81: $25.73M | I81: $5,290,020 | J81: =IFERROR(VALUE(SUBSTITUTE(SUBSTITUTE(Table1[[#This Row],[Volume (24h) USD]],"$",""),",","")),0) -> 5290020 | K81: 1.23B | L81: =IF(OR(LEFT(Table1[[#This Row],[Coin Name]],1)="A",LEFT(Table1[[#This Row],[Coin Name]],1)="E",LEFT(Table1[[#This Row],[Coin Name]],1)="I",LEFT(Table1[[#This Row],[Coin Name]],1)="O",LEFT(Table1[[#This Row],[Coin Name]],1)="U",LEFT(Table1[[#This Row],[Coin Name]],1)="B",LEFT(Table1[[#This Row],[Coin Name]],1)="C",LEFT(Table1[[#This Row],[Coin Name]],1)="D"),"Yes","No") -> No | M81: =VALUE(SUBSTITUTE(C81,"$","")) -> 0.02085 | N81: =M81/(1+D81) -> 0.020590559 | O81: =IF(M81<10,"Up to $10",">= $10") -> Up to $10 | P81: =M81-N81 -> 0.00025944104 | Q81: =F81 -> -0.0126 | R81: =IF(M81<=5,"$0-$5",">$5") -> $0-$5 | S81: =IF(C81<=0.05,"$0-$0.05", IF(C81<=0.5,"$0.05-$0.5", IF(C81<=5,"$0.5-$5", IF(C81<=50,"$5-$50",">$50")))) -> >$50
A82: Klever Coin | B82: KLV | C82: $0.002244 | D82: 0.0042 | E82: =D82 -> 0.0042 | F82: =-D82 -> -0.0042 | G82: =D82 -> 0.0042 | H82: $19.94M | I82: $2,554,402 | J82: =IFERROR(VALUE(SUBSTITUTE(SUBSTITUTE(Table1[[#This Row],[Volume (24h) USD]],"$",""),",","")),0) -> 2554402 | K82: 8.88B | L82: =IF(OR(LEFT(Table1[[#This Row],[Coin Name]],1)="A",LEFT(Table1[[#This Row],[Coin Name]],1)="E",LEFT(Table1[[#This Row],[Coin Name]],1)="I",LEFT(Table1[[#This Row],[Coin Name]],1)="O",LEFT(Table1[[#This Row],[Coin Name]],1)="U",LEFT(Table1[[#This Row],[Coin Name]],1)="B",LEFT(Table1[[#This Row],[Coin Name]],1)="C",LEFT(Table1[[#This Row],[Coin Name]],1)="D"),"Yes","No") -> No | M82: =VALUE(SUBSTITUTE(C82,"$","")) -> 0.002244 | N82: =M82/(1+D82) -> 0.0022346146 | O82: =IF(M82<10,"Up to $10",">= $10") -> Up to $10 | P82: =M82-N82 -> 9.3853814e-06 | Q82: =F82 -> -0.0042 | R82: =IF(M82<=5,"$0-$5",">$5") -> $0-$5 | S82: =IF(C82<=0.05,"$0-$0.05", IF(C82<=0.5,"$0.05-$0.5", IF(C82<=5,"$0.5-$5", IF(C82<=50,"$5-$50",">$50")))) -> >$50
A83: Pups (Bitcoin) | B83: PUPS | C83: $0.02041 | D83: 0.0424 | E83: =D83 -> 0.0424 | F83: =-D83 -> -0.0424 | G83: =D83 -> 0.0424 | H83: $19.77M | I83: $174,082 | J83: =IFERROR(VALUE(SUBSTITUTE(SUBSTITUTE(Table1[[#This Row],[Volume (24h) USD]],"$",""),",","")),0) -> 174082 | K83: 968.44M | L83: =IF(OR(LEFT(Table1[[#This Row],[Coin Name]],1)="A",LEFT(Table1[[#This Row],[Coin Name]],1)="E",LEFT(Table1[[#This Row],[Coin Name]],1)="I",LEFT(Table1[[#This Row],[Coin Name]],1)="O",LEFT(Table1[[#This Row],[Coin Name]],1)="U",LEFT(Table1[[#This Row],[Coin Name]],1)="B",LEFT(Table1[[#This Row],[Coin Name]],1)="C",LEFT(Table1[[#This Row],[Coin Name]],1)="D"),"Yes","No") -> No | M83: =VALUE(SUBSTITUTE(C83,"$","")) -> 0.02041 | N83: =M83/(1+D83) -> 0.019579816 | O83: =IF(M83<10,"Up to $10",">= $10") -> Up to $10 | P83: =M83-N83 -> 0.00083018419 | Q83: =F83 -> -0.0424 | R83: =IF(M83<=5,"$0-$5",">$5") -> $0-$5 | S83: =IF(C83<=0.05,"$0-$0.05", IF(C83<=0.5,"$0.05-$0.5", IF(C83<=5,"$0.5-$5", IF(C83<=50,"$5-$50",">$50")))) -> >$50
A84: NATIX Network | B84: NATIX | C84: $0.001223 | D84: 0.0002 | E84: =D84 -> 0.0002 | F84: =-D84 -> -0.0002 | G84: =D84 -> 0.0002 | H84: $19.74M | I84: $362,962 | J84: =IFERROR(VALUE(SUBSTITUTE(SUBSTITUTE(Table1[[#This Row],[Volume (24h) USD]],"$",""),",","")),0) -> 362962 | K84: 16.13B | L84: =IF(OR(LEFT(Table1[[#This Row],[Coin Name]],1)="A",LEFT(Table1[[#This Row],[Coin Name]],1)="E",LEFT(Table1[[#This Row],[Coin Name]],1)="I",LEFT(Table1[[#This Row],[Coin Name]],1)="O",LEFT(Table1[[#This Row],[Coin Name]],1)="U",LEFT(Table1[[#This Row],[Coin Name]],1)="B",LEFT(Table1[[#This Row],[Coin Name]],1)="C",LEFT(Table1[[#This Row],[Coin Name]],1)="D"),"Yes","No") -> No | M84: =VALUE(SUBSTITUTE(C84,"$","")) -> 0.001223 | N84: =M84/(1+D84) -> 0.0012227554 | O84: =IF(M84<10,"Up to $10",">= $10") -> Up to $10 | P84: =M84-N84 -> 2.4455109e-07 | Q84: =F84 -> -0.0002 | R84: =IF(M84<=5,"$0-$5",">$5") -> $0-$5 | S84: =IF(C84<=0.05,"$0-$0.05", IF(C84<=0.5,"$0.05-$0.5", IF(C84<=5,"$0.5-$5", IF(C84<=50,"$5-$50",">$50")))) -> >$50
A85: BizAuto | B85: BIZA | C85: $0.0005920 | D85: 0.0068 | E85: =D85 -> 0.0068 | F85: =-D85 -> -0.0068 | G85: =D85 -> 0.0068 | H85: $1.59M | I85: $1,660,204 | J85: =IFERROR(VALUE(SUBSTITUTE(SUBSTITUTE(Table1[[#This Row],[Volume (24h) USD]],"$",""),",","")),0) -> 1660204 | K85: 2.67B | L85: =IF(OR(LEFT(Table1[[#This Row],[Coin Name]],1)="A",LEFT(Table1[[#This Row],[Coin Name]],1)="E",LEFT(Table1[[#This Row],[Coin Name]],1)="I",LEFT(Table1[[#This Row],[Coin Name]],1)="O",LEFT(Table1[[#This Row],[Coin Name]],1)="U",LEFT(Table1[[#This Row],[Coin Name]],1)="B",LEFT(Table1[[#This Row],[Coin Name]],1)="C",LEFT(Table1[[#This Row],[Coin Name]],1)="D"),"Yes","No") -> Yes | M85: =VALUE(SUBSTITUTE(C85,"$","")) -> 0.000592 | N85: =M85/(1+D85) -> 0.00058800159 | O85: =IF(M85<10,"Up to $10",">= $10") -> Up to $10 | P85: =M85-N85 -> 3.9984108e-06 | Q85: =F85 -> -0.0068 | R85: =IF(M85<=5,"$0-$5",">$5") -> $0-$5 | S85: =IF(M85<=0.05,"$0-$0.05",IF(M85<=0.5,"$0.05-$0.5",IF(M85<=5,"$0.5-$5",IF(M85<=50,"$5-$50",">$50")))) -> $0-$0.05
A86: Comtech Gold | B86: CGO | C86: $108.17 | D86: 0.0006 | E86: =D86 -> 0.0006 | F86: =-D86 -> -0.0006 | G86: =D86 -> 0.0006 | H86: $15.25M | I86: $1,639,272 | J86: =IFERROR(VALUE(SUBSTITUTE(SUBSTITUTE(Table1[[#This Row],[Volume (24h) USD]],"$",""),",","")),0) -> 1639272 | K86: 141K | L86: =IF(OR(LEFT(Table1[[#This Row],[Coin Name]],1)="A",LEFT(Table1[[#This Row],[Coin Name]],1)="E",LEFT(Table1[[#This Row],[Coin Name]],1)="I",LEFT(Table1[[#This Row],[Coin Name]],1)="O",LEFT(Table1[[#This Row],[Coin Name]],1)="U",LEFT(Table1[[#This Row],[Coin Name]],1)="B",LEFT(Table1[[#This Row],[Coin Name]],1)="C",LEFT(Table1[[#This Row],[Coin Name]],1)="D"),"Yes","No") -> Yes | M86: =VALUE(SUBSTITUTE(C86,"$","")) -> 108.17 | N86: =M86/(1+D86) -> 108.10514 | O86: =IF(M86<10,"Up to $10",">= $10") -> >= $10 | P86: =M86-N86 -> 0.064863082 | Q86: =F86 -> -0.0006 | R86: =IF(M86<=5,"$0-$5",">$5") -> >$5 | S86: =IF(M86<=0.05,"$0-$0.05",IF(M86<=0.5,"$0.05-$0.5",IF(M86<=5,"$0.5-$5",IF(M86<=50,"$5-$50",">$50")))) -> >$50
A87: ANDY (ETH) | B87: ANDY | C87: $0.00005125 | D87: 0.0057 | E87: =D87 -> 0.0057 | F87: =-D87 -> -0.0057 | G87: =D87 -> 0.0057 | H87: $51.26M | I87: $1,414,981 | J87: =IFERROR(VALUE(SUBSTITUTE(SUBSTITUTE(Table1[[#This Row],[Volume (24h) USD]],"$",""),",","")),0) -> 1414981 | K87: 1T | L87: =IF(OR(LEFT(Table1[[#This Row],[Coin Name]],1)="A",LEFT(Table1[[#This Row],[Coin Name]],1)="E",LEFT(Table1[[#This Row],[Coin Name]],1)="I",LEFT(Table1[[#This Row],[Coin Name]],1)="O",LEFT(Table1[[#This Row],[Coin Name]],1)="U",LEFT(Table1[[#This Row],[Coin Name]],1)="B",LEFT(Table1[[#This Row],[Coin Name]],1)="C",LEFT(Table1[[#This Row],[Coin Name]],1)="D"),"Yes","No") -> Yes | M87: =VALUE(SUBSTITUTE(C87,"$","")) -> 5.125e-05 | N87: =M87/(1+D87) -> 5.0959531e-05 | O87: =IF(M87<10,"Up to $10",">= $10") -> Up to $10 | P87: =M87-N87 -> 2.9046932e-07 | Q87: =F87 -> -0.0057 | R87: =IF(M87<=5,"$0-$5",">$5") -> $0-$5 | S87: =IF(M87<=0.05,"$0-$0.05",IF(M87<=0.5,"$0.05-$0.5",IF(M87<=5,"$0.5-$5",IF(M87<=50,"$5-$50",">$50")))) -> $0-$0.05
A88: League of Kingdoms Arena | B88: LOKA | C88: $0.05197 | D88: 0.0104 | E88: =D88 -> 0.0104 | F88: =-D88 -> -0.0104 | G88: =D88 -> 0.0104 | H88: $19.56M | I88: $2,452,497 | J88: =IFERROR(VALUE(SUBSTITUTE(SUBSTITUTE(Table1[[#This Row],[Volume (24h) USD]],"$",""),",","")),0) -> 2452497 | K88: 376.38M | L88: =IF(OR(LEFT(Table1[[#This Row],[Coin Name]],1)="A",LEFT(Table1[[#This Row],[Coin Name]],1)="E",LEFT(Table1[[#This Row],[Coin Name]],1)="I",LEFT(Table1[[#This Row],[Coin Name]],1)="O",LEFT(Table1[[#This Row],[Coin Name]],1)="U",LEFT(Table1[[#This Row],[Coin Name]],1)="B",LEFT(Table1[[#This Row],[Coin Name]],1)="C",LEFT(Table1[[#This Row],[Coin Name]],1)="D"),"Yes","No") -> No | M88: =VALUE(SUBSTITUTE(C88,"$","")) -> 0.05197 | N88: =M88/(1+D88) -> 0.051435075 | O88: =IF(M88<10,"Up to $10",">= $10") -> Up to $10 | P88: =M88-N88 -> 0.00053492478 | Q88: =F88 -> -0.0104 | R88: =IF(M88<=5,"$0-$5",">$5") -> $0-$5 | S88: =IF(C88<=0.05,"$0-$0.05", IF(C88<=0.5,"$0.05-$0.5", IF(C88<=5,"$0.5-$5", IF(C88<=50,"$5-$50",">$50")))) -> >$50
A89: Mango | B89: MNGO | C89: $0.01749 | D89: 0.0055 | E89: =D89 -> 0.0055 | F89: =-D89 -> -0.0055 | G89: =D89 -> 0.0055 | H89: $19.55M | I89: $45 | J89: =IFERROR(VALUE(SUBSTITUTE(SUBSTITUTE(Table1[[#This Row],[Volume (24h) USD]],"$",""),",","")),0) -> 45 | K89: 1.11B | L89: =IF(OR(LEFT(Table1[[#This Row],[Coin Name]],1)="A",LEFT(Table1[[#This Row],[Coin Name]],1)="E",LEFT(Table1[[#This Row],[Coin Name]],1)="I",LEFT(Table1[[#This Row],[Coin Name]],1)="O",LEFT(Table1[[#This Row],[Coin Name]],1)="U",LEFT(Table1[[#This Row],[Coin Name]],1)="B",LEFT(Table1[[#This Row],[Coin Name]],1)="C",LEFT(Table1[[#This Row],[Coin Name]],1)="D"),"Yes","No") -> No | M89: =VALUE(SUBSTITUTE(C89,"$","")) -> 0.01749 | N89: =M89/(1+D89) -> 0.017394331 | O89: =IF(M89<10,"Up to $10",">= $10") -> Up to $10 | P89: =M89-N89 -> 9.5668821e-05 | Q89: =F89 -> -0.0055 | R89: =IF(M89<=5,"$0-$5",">$5") -> $0-$5 | S89: =IF(C89<=0.05,"$0-$0.05", IF(C89<=0.5,"$0.05-$0.5", IF(C89<=5,"$0.5-$5", IF(C89<=50,"$5-$50",">$50")))) -> >$50
A90: Dora Factory | B90: DORA | C90: $0.02198 | D90: 0.0141 | E90: =D90 -> 0.0141 | F90: =-D90 -> -0.0141 | G90: =D90 -> 0.0141 | H90: $11.81M | I90: $1,407,422 | J90: =IFERROR(VALUE(SUBSTITUTE(SUBSTITUTE(Table1[[#This Row],[Volume (24h) USD]],"$",""),",","")),0) -> 1407422 | K90: 537.27M | L90: =IF(OR(LEFT(Table1[[#This Row],[Coin Name]],1)="A",LEFT(Table1[[#This Row],[Coin Name]],1)="E",LEFT(Table1[[#This Row],[Coin Name]],1)="I",LEFT(Table1[[#This Row],[Coin Name]],1)="O",LEFT(Table1[[#This Row],[Coin Name]],1)="U",LEFT(Table1[[#This Row],[Coin Name]],1)="B",LEFT(Table1[[#This Row],[Coin Name]],1)="C",LEFT(Table1[[#This Row],[Coin Name]],1)="D"),"Yes","No") -> Yes | M90: =VALUE(SUBSTITUTE(C90,"$","")) -> 0.02198 | N90: =M90/(1+D90) -> 0.021674391 | O90: =IF(M90<10,"Up to $10",">= $10") -> Up to $10 | P90: =M90-N90 -> 0.00030560891 | Q90: =F90 -> -0.0141 | R90: =IF(M90<=5,"$0-$5",">$5") -> $0-$5 | S90: =IF(M90<=0.05,"$0-$0.05",IF(M90<=0.5,"$0.05-$0.5",IF(M90<=5,"$0.5-$5",IF(M90<=50,"$5-$50",">$50")))) -> $0-$0.05
A91: dKargo | B91: DKA | C91: $0.01544 | D91: 0.0017 | E91: =D91 -> 0.0017 | F91: =-D91 -> -0.0017 | G91: =D91 -> 0.0017 | H91: $72.37M | I91: $1,356,568 | J91: =IFERROR(VALUE(SUBSTITUTE(SUBSTITUTE(Table1[[#This Row],[Volume (24h) USD]],"$",""),",","")),0) -> 1356568 | K91: 4.68B | L91: =IF(OR(LEFT(Table1[[#This Row],[Coin Name]],1)="A",LEFT(Table1[[#This Row],[Coin Name]],1)="E",LEFT(Table1[[#This Row],[Coin Name]],1)="I",LEFT(Table1[[#This Row],[Coin Name]],1)="O",LEFT(Table1[[#This Row],[Coin Name]],1)="U",LEFT(Table1[[#This Row],[Coin Name]],1)="B",LEFT(Table1[[#This Row],[Coin Name]],1)="C",LEFT(Table1[[#This Row],[Coin Name]],1)="D"),"Yes","No") -> Yes | M91: =VALUE(SUBSTITUTE(C91,"$","")) -> 0.01544 | N91: =M91/(1+D91) -> 0.015413797 | O91: =IF(M91<10,"Up to $10",">= $10") -> Up to $10 | P91: =M91-N91 -> 2.6203454e-05 | Q91: =F91 -> -0.0017 | R91: =IF(M91<=5,"$0-$5",">$5") -> $0-$5 | S91: =IF(M91<=0.05,"$0-$0.05",IF(M91<=0.5,"$0.05-$0.5",IF(M91<=5,"$0.5-$5",IF(M91<=50,"$5-$50",">$50")))) -> $0-$0.05
A92: Port3 Network | B92: PORT3 | C92: $0.04410 | D92: 0.0096 | E92: =D92 -> 0.0096 | F92: =-D92 -> -0.0096 | G92: =D92 -> 0.0096 | H92: $15.61M | I92: $4,797,522 | J92: =IFERROR(VALUE(SUBSTITUTE(SUBSTITUTE(Table1[[#This Row],[Volume (24h) USD]],"$",""),",","")),0) -> 4797522 | K92: 353.95M | L92: =IF(OR(LEFT(Table1[[#This Row],[Coin Name]],1)="A",LEFT(Table1[[#This Row],[Coin Name]],1)="E",LEFT(Table1[[#This Row],[Coin Name]],1)="I",LEFT(Table1[[#This Row],[Coin Name]],1)="O",LEFT(Table1[[#This Row],[Coin Name]],1)="U",LEFT(Table1[[#This Row],[Coin Name]],1)="B",LEFT(Table1[[#This Row],[Coin Name]],1)="C",LEFT(Table1[[#This Row],[Coin Name]],1)="D"),"Yes","No") -> No | M92: =VALUE(SUBSTITUTE(C92,"$","")) -> 0.0441 | N92: =M92/(1+D92) -> 0.043680666 | O92: =IF(M92<10,"Up to $10",">= $10") -> Up to $10 | P92: =M92-N92 -> 0.00041933439 | Q92: =F92 -> -0.0096 | R92: =IF(M92<=5,"$0-$5",">$5") -> $0-$5 | S92: =IF(C92<=0.05,"$0-$0.05", IF(C92<=0.5,"$0.05-$0.5", IF(C92<=5,"$0.5-$5", IF(C92<=50,"$5-$50",">$50")))) -> >$50
A93: SIX Token | B93: SIX | C93: $0.01837 | D93: 0.004 | E93: =D93 -> 0.004 | F93: =-D93 -> -0.004 | G93: =D93 -> 0.004 | H93: $15.63M | I93: $884,405 | J93: =IFERROR(VALUE(SUBSTITUTE(SUBSTITUTE(Table1[[#This Row],[Volume (24h) USD]],"$",""),",","")),0) -> 884405 | K93: 850.96M | L93: =IF(OR(LEFT(Table1[[#This Row],[Coin Name]],1)="A",LEFT(Table1[[#This Row],[Coin Name]],1)="E",LEFT(Table1[[#This Row],[Coin Name]],1)="I",LEFT(Table1[[#This Row],[Coin Name]],1)="O",LEFT(Table1[[#This Row],[Coin Name]],1)="U",LEFT(Table1[[#This Row],[Coin Name]],1)="B",LEFT(Table1[[#This Row],[Coin Name]],1)="C",LEFT(Table1[[#This Row],[Coin Name]],1)="D"),"Yes","No") -> No | M93: =VALUE(SUBSTITUTE(C93,"$","")) -> 0.01837 | N93: =M93/(1+D93) -> 0.018296813 | O93: =IF(M93<10,"Up to $10",">= $10") -> Up to $10 | P93: =M93-N93 -> 7.3187251e-05 | Q93: =F93 -> -0.004 | R93: =IF(M93<=5,"$0-$5",">$5") -> $0-$5 | S93: =IF(C93<=0.05,"$0-$0.05", IF(C93<=0.5,"$0.05-$0.5", IF(C93<=5,"$0.5-$5", IF(C93<=50,"$5-$50",">$50")))) -> >$50
A94: Ertha | B94: ERTHA | C94: $0.0006265 | D94: 0.0019 | E94: =D94 -> 0.0019 | F94: =-D94 -> -0.0019 | G94: =D94 -> 0.0019 | H94: $1.24M | I94: $1,332,029 | J94: =IFERROR(VALUE(SUBSTITUTE(SUBSTITUTE(Table1[[#This Row],[Volume (24h) USD]],"$",""),",","")),0) -> 1332029 | K94: 1.97B | L94: =IF(OR(LEFT(Table1[[#This Row],[Coin Name]],1)="A",LEFT(Table1[[#This Row],[Coin Name]],1)="E",LEFT(Table1[[#This Row],[Coin Name]],1)="I",LEFT(Table1[[#This Row],[Coin Name]],1)="O",LEFT(Table1[[#This Row],[Coin Name]],1)="U",LEFT(Table1[[#This Row],[Coin Name]],1)="B",LEFT(Table1[[#This Row],[Coin Name]],1)="C",LEFT(Table1[[#This Row],[Coin Name]],1)="D"),"Yes","No") -> Yes | M94: =VALUE(SUBSTITUTE(C94,"$","")) -> 0.0006265 | N94: =M94/(1+D94) -> 0.00062531191 | O94: =IF(M94<10,"Up to $10",">= $10") -> Up to $10 | P94: =M94-N94 -> 1.1880926e-06 | Q94: =F94 -> -0.0019 | R94: =IF(M94<=5,"$0-$5",">$5") -> $0-$5 | S94: =IF(M94<=0.05,"$0-$0.05",IF(M94<=0.5,"$0.05-$0.5",IF(M94<=5,"$0.5-$5",IF(M94<=50,"$5-$50",">$50")))) -> $0-$0.05
A95: Department Of Government Efficiency (dogegov.com) | B95: DOGE | C95: $0.009443 | D95: 0.0139 | E95: =D95 -> 0.0139 | F95: =-D95 -> -0.0139 | G95: =D95 -> 0.0139 | H95: $9.25M | I95: $1,315,522 | J95: =IFERROR(VALUE(SUBSTITUTE(SUBSTITUTE(Table1[[#This Row],[Volume (24h) USD]],"$",""),",","")),0) -> 1315522 | K95: 979.12M | L95: =IF(OR(LEFT(Table1[[#This Row],[Coin Name]],1)="A",LEFT(Table1[[#This Row],[Coin Name]],1)="E",LEFT(Table1[[#This Row],[Coin Name]],1)="I",LEFT(Table1[[#This Row],[Coin Name]],1)="O",LEFT(Table1[[#This Row],[Coin Name]],1)="U",LEFT(Table1[[#This Row],[Coin Name]],1)="B",LEFT(Table1[[#This Row],[Coin Name]],1)="C",LEFT(Table1[[#This Row],[Coin Name]],1)="D"),"Yes","No") -> Yes | M95: =VALUE(SUBSTITUTE(C95,"$","")) -> 0.009443 | N95: =M95/(1+D95) -> 0.0093135418 | O95: =IF(M95<10,"Up to $10",">= $10") -> Up to $10 | P95: =M95-N95 -> 0.00012945823 | Q95: =F95 -> -0.0139 | R95: =IF(M95<=5,"$0-$5",">$5") -> $0-$5 | S95: =IF(M95<=0.05,"$0-$0.05",IF(M95<=0.5,"$0.05-$0.5",IF(M95<=5,"$0.5-$5",IF(M95<=50,"$5-$50",">$50")))) -> $0-$0.05
A96: Destra Network | B96: DSYNC | C96: $0.1111 | D96: 0.0071 | E96: =D96 -> 0.0071 | F96: =-D96 -> -0.0071 | G96: =D96 -> 0.0071 | H96: $108.35M | I96: $1,068,402 | J96: =IFERROR(VALUE(SUBSTITUTE(SUBSTITUTE(Table1[[#This Row],[Volume (24h) USD]],"$",""),",","")),0) -> 1068402 | K96: 974.94M | L96: =IF(OR(LEFT(Table1[[#This Row],[Coin Name]],1)="A",LEFT(Table1[[#This Row],[Coin Name]],1)="E",LEFT(Table1[[#This Row],[Coin Name]],1)="I",LEFT(Table1[[#This Row],[Coin Name]],1)="O",LEFT(Table1[[#This Row],[Coin Name]],1)="U",LEFT(Table1[[#This Row],[Coin Name]],1)="B",LEFT(Table1[[#This Row],[Coin Name]],1)="C",LEFT(Table1[[#This Row],[Coin Name]],1)="D"),"Yes","No") -> Yes | M96: =VALUE(SUBSTITUTE(C96,"$","")) -> 0.1111 | N96: =M96/(1+D96) -> 0.11031675 | O96: =IF(M96<10,"Up to $10",">= $10") -> Up to $10 | P96: =M96-N96 -> 0.00078324893 | Q96: =F96 -> -0.0071 | R96: =IF(M96<=5,"$0-$5",">$5") -> $0-$5 | S96: =IF(M96<=0.05,"$0-$0.05",IF(M96<=0.5,"$0.05-$0.5",IF(M96<=5,"$0.5-$5",IF(M96<=50,"$5-$50",">$50")))) -> $0.05-$0.5
A97: Paris Saint-Germain Fan Token | B97: PSG | C97: $1.60 | D97: 0.0018 | E97: =D97 -> 0.0018 | F97: =-D97 -> -0.0018 | G97: =D97 -> 0.0018 | H97: $15.31M | I97: $3,216,530 | J97: =IFERROR(VALUE(SUBSTITUTE(SUBSTITUTE(Table1[[#This Row],[Volume (24h) USD]],"$",""),",","")),0) -> 3216530 | K97: 9.55M | L97: =IF(OR(LEFT(Table1[[#This Row],[Coin Name]],1)="A",LEFT(Table1[[#This Row],[Coin Name]],1)="E",LEFT(Table1[[#This Row],[Coin Name]],1)="I",LEFT(Table1[[#This Row],[Coin Name]],1)="O",LEFT(Table1[[#This Row],[Coin Name]],1)="U",LEFT(Table1[[#This Row],[Coin Name]],1)="B",LEFT(Table1[[#This Row],[Coin Name]],1)="C",LEFT(Table1[[#This Row],[Coin Name]],1)="D"),"Yes","No") -> No | M97: =VALUE(SUBSTITUTE(C97,"$","")) -> 1.6 | N97: =M97/(1+D97) -> 1.5971252 | O97: =IF(M97<10,"Up to $10",">= $10") -> Up to $10 | P97: =M97-N97 -> 0.0028748253 | Q97: =F97 -> -0.0018 | R97: =IF(M97<=5,"$0-$5",">$5") -> $0-$5 | S97: =IF(C97<=0.05,"$0-$0.05", IF(C97<=0.5,"$0.05-$0.5", IF(C97<=5,"$0.5-$5", IF(C97<=50,"$5-$50",">$50")))) -> >$50
A98: Daddy Tate | B98: DADDY | C98: $0.03288 | D98: 0.0001 | E98: =D98 -> 0.0001 | F98: =-D98 -> -0.0001 | G98: =D98 -> 0.0001 | H98: $19.72M | I98: $999,710 | J98: =IFERROR(VALUE(SUBSTITUTE(SUBSTITUTE(Table1[[#This Row],[Volume (24h) USD]],"$",""),",","")),0) -> 999710 | K98: 599.63M | L98: =IF(OR(LEFT(Table1[[#This Row],[Coin Name]],1)="A",LEFT(Table1[[#This Row],[Coin Name]],1)="E",LEFT(Table1[[#This Row],[Coin Name]],1)="I",LEFT(Table1[[#This Row],[Coin Name]],1)="O",LEFT(Table1[[#This Row],[Coin Name]],1)="U",LEFT(Table1[[#This Row],[Coin Name]],1)="B",LEFT(Table1[[#This Row],[Coin Name]],1)="C",LEFT(Table1[[#This Row],[Coin Name]],1)="D"),"Yes","No") -> Yes | M98: =VALUE(SUBSTITUTE(C98,"$","")) -> 0.03288 | N98: =M98/(1+D98) -> 0.032876712 | O98: =IF(M98<10,"Up to $10",">= $10") -> Up to $10 | P98: =M98-N98 -> 3.2876712e-06 | Q98: =F98 -> -0.0001 | R98: =IF(M98<=5,"$0-$5",">$5") -> $0-$5 | S98: =IF(M98<=0.05,"$0-$0.05",IF(M98<=0.5,"$0.05-$0.5",IF(M98<=5,"$0.5-$5",IF(M98<=50,"$5-$50",">$50")))) -> $0-$0.05
A99: CrossFi | B99: XFI | C99: $0.09003 | D99: 0.0022 | E99: =D99 -> 0.0022 | F99: =-D99 -> -0.0022 | G99: =D99 -> 0.0022 | H99: $5.24M | I99: $955,799 | J99: =IFERROR(VALUE(SUBSTITUTE(SUBSTITUTE(Table1[[#This Row],[Volume (24h) USD]],"$",""),",","")),0) -> 955799 | K99: 58.23M | L99: =IF(OR(LEFT(Table1[[#This Row],[Coin Name]],1)="A",LEFT(Table1[[#This Row],[Coin Name]],1)="E",LEFT(Table1[[#This Row],[Coin Name]],1)="I",LEFT(Table1[[#This Row],[Coin Name]],1)="O",LEFT(Table1[[#This Row],[Coin Name]],1)="U",LEFT(Table1[[#This Row],[Coin Name]],1)="B",LEFT(Table1[[#This Row],[Coin Name]],1)="C",LEFT(Table1[[#This Row],[Coin Name]],1)="D"),"Yes","No") -> Yes | M99: =VALUE(SUBSTITUTE(C99,"$","")) -> 0.09003 | N99: =M99/(1+D99) -> 0.089832369 | O99: =IF(M99<10,"Up to $10",">= $10") -> Up to $10 | P99: =M99-N99 -> 0.00019763121 | Q99: =F99 -> -0.0022 | R99: =IF(M99<=5,"$0-$5",">$5") -> $0-$5 | S99: =IF(M99<=0.05,"$0-$0.05",IF(M99<=0.5,"$0.05-$0.5",IF(M99<=5,"$0.5-$5",IF(M99<=50,"$5-$50",">$50")))) -> $0.05-$0.5
A100: Dohrnii | B100: DHN | C100: $2.13 | D100: 0.0005 | E100: =D100 -> 0.0005 | F100: =-D100 -> -0.0005 | G100: =D100 -> 0.0005 | H100: $36.4M | I100: $867,656 | J100: =IFERROR(VALUE(SUBSTITUTE(SUBSTITUTE(Table1[[#This Row],[Volume (24h) USD]],"$",""),",","")),0) -> 867656 | K100: 17.07M | L100: =IF(OR(LEFT(Table1[[#This Row],[Coin Name]],1)="A",LEFT(Table1[[#This Row],[Coin Name]],1)="E",LEFT(Table1[[#This Row],[Coin Name]],1)="I",LEFT(Table1[[#This Row],[Coin Name]],1)="O",LEFT(Table1[[#This Row],[Coin Name]],1)="U",LEFT(Table1[[#This Row],[Coin Name]],1)="B",LEFT(Table1[[#This Row],[Coin Name]],1)="C",LEFT(Table1[[#This Row],[Coin Name]],1)="D"),"Yes","No") -> Yes | M100: =VALUE(SUBSTITUTE(C100,"$","")) -> 2.13 | N100: =M100/(1+D100) -> 2.1289355 | O100: =IF(M100<10,"Up to $10",">= $10") -> Up to $10 | P100: =M100-N100 -> 0.0010644678 | Q100: =F100 -> -0.0005 | R100: =IF(M100<=5,"$0-$5",">$5") -> $0-$5 | S100: =IF(M100<=0.05,"$0-$0.05",IF(M100<=0.5,"$0.05-$0.5",IF(M100<=5,"$0.5-$5",IF(M100<=50,"$5-$50",">$50")))) -> $0.5-$5
...

Sheet task1_dashboard
D1: CRYPTO ANALYSIS DASHBOARD
A3: Coin Name | B3: Volume Num
A4: Bitcoin | B4: 43170391288 | E4: Please open in working hours (9 am to 5 pm)
A5: Ethereum | B5: 14942260356
A6: USDC | B6: 8208315257
A7: BNB | B7: 1497928447
A8: Dogecoin | B8: 781433558
A9: Cardano | B9: 539447597
A10: Orbiter Finance | B10: 40860347
A11: Usual | B11: 25758134
A12: Decentraland | B12: 25685731
A13: Eurite | B13: 22680605

Sheet Task2_Dashboard
A1: CRYPTO COIN COMPARISON DASHBOARD
A2: coin 1 name | B2: Bitcoin
A3: coin 2 name | B3: Ethereum
A6: field | B6: coin 1 | C6: coin 2
F7: Volume Difference | G7: =ABS(_xlfn.NUMBERVALUE(SUBSTITUTE(B10,"$",""))-_xlfn.NUMBERVALUE(SUBSTITUTE(C10,"$",""))) -> 28228130932
A8: symbol | B8: =_xlfn.XLOOKUP($B$2,'raw data'!$A:$A,'raw data'!$B:$B) -> BTC | C8: =_xlfn.XLOOKUP($B$3,'raw data'!$A:$A,'raw data'!$B:$B) -> ETH | F8: Market Cap Difference | G8: =B11&" vs "&C11 -> $2.07T vs $299.51B
A9: price | B9: =_xlfn.XLOOKUP($B$2,'raw data'!$A:$A,'raw data'!$C:$C) -> $104,058.04 | C9: =_xlfn.XLOOKUP($B$3,'raw data'!$A:$A,'raw data'!$C:$C) -> $2,483.59 | F9: Supply Difference | G9: =B12&" vs "&C12 -> 19.88M vs 120.72M
A10: volume | B10: =_xlfn.XLOOKUP($B$2,'raw data'!$A:$A,'raw data'!$I:$I) -> $43,170,391,288 | C10: =_xlfn.XLOOKUP($B$3,'raw data'!$A:$A,'raw data'!$I:$I) -> $14,942,260,356
A11: market cap | B11: =_xlfn.XLOOKUP($B$2,'raw data'!$A:$A,'raw data'!$H:$H) -> $2.07T | C11: =_xlfn.XLOOKUP($B$3,'raw data'!$A:$A,'raw data'!$H:$H) -> $299.51B
A12: circulating supply | B12: =_xlfn.XLOOKUP($B$2,'raw data'!$A:$A,'raw data'!$K:$K) -> 19.88M | C12: =_xlfn.XLOOKUP($B$3,'raw data'!$A:$A,'raw data'!$K:$K) -> 120.72M

Sheet Task 3_Liquidity
A1: TOP 5 CRYPTO LIQUIDITY ANALYSIS
M3: Summary table
A4: Row Labels | B4: Sum of volume num | M4: Coin | N4: Volume
A5: USDC | B5: 8208315257 | M5: USDC | N5: 8208315257
A6: $0-$50 | B6: 8208315257 | M6: Dogecoin | N6: 781433558
A7: Dogecoin | B7: 781433558 | M7: Cardano | N7: 539447597
A8: $0-$50 | B8: 781433558 | M8: Orbiter Finance | N8: 40860347
A9: Cardano | B9: 539447597 | M9: Usual | N9: 25758134
A10: $0-$50 | B10: 539447597
A11: Orbiter Finance | B11: 40860347
A12: $0-$50 | B12: 40860347
A13: Usual | B13: 25758134
A14: $0-$50 | B14: 25758134
A15: Grand Total | B15: 9595814893

Sheet Task4_Price_Analysis
A1: TOP 10 PRICE CHANGE ANALYSIS
A3: Coin Name | B3: =A8 -> Bitcoin
A4: Symbol | B4: =A9 -> BTC
A5: Price change | B5: =B8 -> 249.14136
A7: Row Labels | B7: Sum of price change
A8: Bitcoin | B8: 249.14136
A9: BTC | B9: 249.14136
A10: Ethereum | B10: 18.732914
A11: ETH | B11: 18.732914
A12: DeFi Pulse Index | B12: 2.4807333
A13: DPI | B13: 2.4807333
A14: Solana | B14: 1.398587
A15: SOL | B15: 1.398587
A16: BNB | B16: 0.64414585
A17: BNB | B17: 0.64414585
A18: Beefy | B18: 0.23469649
A19: BIFI | B19: 0.23469649
... A28: Grand Total | B28: 272.75502

Sheet Task5_Historical_Insights
A1: HISTORICAL PRICE CHANGE INSIGHTS
A2: task5 range | B2: $0-$5
A4: Row Labels | B4: Sum of 1h change | C4: Sum of 7d change | D4: Sum of 24 hr change
A5: Bitcoin 2 | B5: 0.0334 | C5: 0.0334 | D5: -0.0334
A6: Ctrl Wallet | B6: 0.1879 | C6: 0.1879 | D6: -0.1879
A7: Degen | B7: 0.0342 | C7: 0.0342 | D7: -0.0342
A8: Kin | B8: 0.0464 | C8: 0.0464 | D8: -0.0464
A9: LanLan Cat | B9: 0.1177 | C9: 0.1177 | D9: -0.1177
A10: Maple Finance | B10: 0.0305 | C10: 0.0305 | D10: -0.0305
A11: Orbiter Finance | B11: 0.0427 | C11: 0.0427 | D11: -0.0427
A12: PIBBLE | B12: 0.0405 | C12: 0.0405 | D12: -0.0405
A13: Pups (Bitcoin) | B13: 0.0424 | C13: 0.0424 | D13: -0.0424
A14: would | B14: 0.0303 | C14: 0.0303 | D14: -0.0303
A15: Grand Total | B15: 0.606 | C15: 0.606 | D15: -0.606

Sheet Task6_LowBudget_Insights
A1: Range | B1: >$50 | E1: LOW BUDGET INVESTMENT KPI DASHBOARD
A2: price range | B2: (All)
E3: coin name | F3: =A5 -> LanLan Cat
A4: Row Labels | B4: Average of average downfall | E4: symbol | F4: =VLOOKUP(F3,'raw data'!A:C,2,FALSE) -> LANLAN
A5: LanLan Cat | B5: -0.1177 | E5: price | F5: =VLOOKUP(F3,'raw data'!A:C,3,FALSE) -> $0.0001380
A6: Kin | B6: -0.0464 | E6: average downfall | F6: =B5 -> -0.1177
A7: Pups (Bitcoin) | B7: -0.0424 | E7: total coins | F7: =COUNTA(A5:A500) -> 121
A8: PIBBLE | B8: -0.0405
A9: Maple Finance | B9: -0.0305
A10: would | B10: -0.0303
A11: Torum | B11: -0.0294
A12: DeFi Pulse Index | B12: -0.0282
A13: Sentio AI | B13: -0.0267
A14: Step Finance | B14: -0.0251
A15: Hoge Finance | B15: -0.0248
A16: Spark | B16: -0.0244
A17: Pyth Network | B17: -0.0227
A18: Fractal Bitcoin | B18: -0.0219
A19: Koma Inu | B19: -0.0218
... A125: Grand Total | B125: -0.0098466667

Sheet Task3 table 
A1: Coin Name | B1: Price (USD) | C1: Volume (24h) USD | D1: volume num | E1: price range
A2: Bitcoin | B2: $104,058.04 | C2: $43,170,391,288 | D2: 43170391288 | E2: =IF(VALUE(SUBSTITUTE(B2,"$",""))<=50,"$0-$50","> $50") -> > $50
A3: Ethereum | B3: $2,483.59 | C3: $14,942,260,356 | D3: 14942260356 | E3: =IF(VALUE(SUBSTITUTE(B3,"$",""))<=50,"$0-$50","> $50") -> > $50
A4: USDC | B4: $0.9998 | C4: $8,208,315,257 | D4: 8208315257 | E4: =IF(VALUE(SUBSTITUTE(B4,"$",""))<=50,"$0-$50","> $50") -> $0-$50
A5: BNB | B5: $644.79 | C5: $1,497,928,447 | D5: 1497928447 | E5: =IF(VALUE(SUBSTITUTE(B5,"$",""))<=50,"$0-$50","> $50") -> > $50
A6: Dogecoin | B6: $0.1654 | C6: $781,433,558 | D6: 781433558 | E6: =IF(VALUE(SUBSTITUTE(B6,"$",""))<=50,"$0-$50","> $50") -> $0-$50
A7: Cardano | B7: $0.5808 | C7: $539,447,597 | D7: 539447597 | E7: =IF(VALUE(SUBSTITUTE(B7,"$",""))<=50,"$0-$50","> $50") -> $0-$50
A8: Orbiter Finance | B8: $0.008376 | C8: $40,860,347 | D8: 40860347 | E8: =IF(VALUE(SUBSTITUTE(B8,"$",""))<=50,"$0-$50","> $50") -> $0-$50
A9: Usual | B9: $0.07198 | C9: $25,758,134 | D9: 25758134 | E9: =IF(VALUE(SUBSTITUTE(B9,"$",""))<=50,"$0-$50","> $50") -> $0-$50
A10: Decentraland | B10: $0.2505 | C10: $25,685,731 | D10: 25685731 | E10: =IF(VALUE(SUBSTITUTE(B10,"$",""))<=50,"$0-$50","> $50") -> $0-$50
A11: Eurite | B11: $1.15 | C11: $22,680,605 | D11: 22680605 | E11: =IF(VALUE(SUBSTITUTE(B11,"$",""))<=50,"$0-$50","> $50") -> $0-$50
A12: Core | B12: $0.5443 | C12: $14,386,742 | D12: 14386742 | E12: =IF(VALUE(SUBSTITUTE(B12,"$",""))<=50,"$0-$50","> $50") -> $0-$50
A13: Aevo | B13: $0.07876 | C13: $12,716,009 | D13: 12716009 | E13: =IF(VALUE(SUBSTITUTE(B13,"$",""))<=50,"$0-$50","> $50") -> $0-$50
... A87: DeHub | B87: $0.0003842 | C87: N/A | D87: 0 | E87: =IF(VALUE(SUBSTITUTE(B87,"$",""))<=50,"$0-$50","> $50") -> $0-$50
